{
  "_class": "group",
  "booleanOperation": -1,
  "do_objectID": "5F83A66A-AFCA-4753-8410-4BBDE9A15F4E",
  "exportOptions": {
    "_class": "exportOptions",
    "do_objectID": "0D3CB7D1-80DB-470A-8AF1-F51EACBA0F83",
    "exportFormats": [
    ],
    "includedLayerIds": [
    ],
    "layerOptions": 0,
    "shouldTrim": false
  },
  "frame": {
    "_class": "rect",
    "constrainProportions": false,
    "do_objectID": "D7DF20E7-C1C0-4776-A85E-E4A6141CE94E",
    "height": 32,
    "width": 71,
    "x": 148,
    "y": 88
  },
  "hasClickThrough": false,
  "isFixedToViewport": false,
  "isFlippedHorizontal": false,
  "isFlippedVertical": false,
  "isLocked": false,
  "isVisible": true,
  "layerListExpandedType": 0,
  "layers": [
    {
      "class": "shapeGroup",
      "id": "F8A680D8-C42E-4443-A8E9-6CB5D3182165"
    },
    {
      "class": "text",
      "id": "10BC461F-13A6-4960-9543-36CB84694A0A"
    }
  ],
  "name": "助记词2",
  "nameIsFixed": false,
  "resizingConstraint": 63,
  "resizingType": 0,
  "rotation": 0,
  "shouldBreakMaskChain": false,
  "style": {
    "_class": "style",
    "do_objectID": "7C0A0803-CF6D-4532-8589-0D3644E31E54",
    "endMarkerType": 0,
    "miterLimit": 10,
    "startMarkerType": 0,
    "windingRule": 1
  }
}