{
  "_class": "group",
  "booleanOperation": 0,
  "do_objectID": "60D15A5E-0F45-427E-88BA-C09FECC9A32A",
  "exportOptions": {
    "_class": "exportOptions",
    "do_objectID": "6C696FD2-48AC-4B0F-9B52-07E887D68BA9",
    "exportFormats": [
    ],
    "includedLayerIds": [
    ],
    "layerOptions": 0,
    "shouldTrim": false
  },
  "frame": {
    "_class": "rect",
    "constrainProportions": false,
    "do_objectID": "97AF04A2-4F4D-49C5-B5E6-214F38AF3182",
    "height": 24,
    "width": 24,
    "x": 14,
    "y": 10
  },
  "hasClickThrough": false,
  "isFixedToViewport": false,
  "isFlippedHorizontal": false,
  "isFlippedVertical": false,
  "isLocked": false,
  "isVisible": true,
  "layerListExpandedType": 1,
  "layers": [
    {
      "class": "slice",
      "id": "BAEF5CA9-F6FD-4C0C-93B2-60DD0ACEF9CA"
    },
    {
      "class": "shapeGroup",
      "id": "0EDD254C-C67A-4560-96BB-A3BF46E8B95E"
    }
  ],
  "name": "ic_notify_back",
  "nameIsFixed": true,
  "resizingConstraint": 63,
  "resizingType": 0,
  "rotation": 0,
  "shouldBreakMaskChain": false,
  "style": {
    "_class": "style",
    "do_objectID": "E28182B0-B547-493E-AB07-B1C980773D41",
    "endMarkerType": 0,
    "miterLimit": 10,
    "startMarkerType": 0,
    "windingRule": 1
  }
}