{
  "_class": "shapeGroup",
  "booleanOperation": 0,
  "clippingMaskMode": 0,
  "do_objectID": "45AE505B-BF7C-4B3E-A27B-A4CF42F53024",
  "exportOptions": {
    "_class": "exportOptions",
    "do_objectID": "95728312-C92E-4F6C-A2C5-C5E524056B30",
    "exportFormats": [
    ],
    "includedLayerIds": [
    ],
    "layerOptions": 0,
    "shouldTrim": false
  },
  "frame": {
    "_class": "rect",
    "constrainProportions": false,
    "do_objectID": "404F5C40-14A9-4346-88CB-32196439047D",
    "height": 812,
    "width": 375,
    "x": 0,
    "y": 0
  },
  "hasClickThrough": false,
  "hasClippingMask": false,
  "isFixedToViewport": false,
  "isFlippedHorizontal": false,
  "isFlippedVertical": false,
  "isLocked": false,
  "isVisible": true,
  "layerListExpandedType": 0,
  "layers": [
    {
      "class": "rectangle",
      "id": "511ABDA0-4199-457D-B6AD-35417A21B6FA"
    }
  ],
  "name": "Modal Overlay",
  "nameIsFixed": false,
  "originalObjectID": "F10C3721-615E-40B0-B65D-D8FE7E1AA8F1",
  "resizingConstraint": 63,
  "resizingType": 0,
  "rotation": 0,
  "shouldBreakMaskChain": false,
  "style": {
    "_class": "style",
    "do_objectID": "8022116F-D111-49E4-BC39-E585366A37A3",
    "endMarkerType": 0,
    "fills": [
      {
        "_class": "fill",
        "color": {
          "_class": "color",
          "alpha": 0.4,
          "blue": 0,
          "green": 0,
          "red": 0
        },
        "fillType": 0,
        "isEnabled": true,
        "noiseIndex": 0,
        "noiseIntensity": 0,
        "patternFillType": 0,
        "patternTileScale": 1
      },
      {
        "_class": "fill",
        "color": {
          "_class": "color",
          "alpha": 1,
          "blue": 0,
          "green": 0,
          "red": 0
        },
        "contextSettings": {
          "_class": "graphicsContextSettings",
          "blendMode": 12,
          "opacity": 1
        },
        "fillType": 0,
        "gradient": {
          "_class": "gradient",
          "elipseLength": 0,
          "from": "{0.5, 0}",
          "gradientType": 0,
          "stops": [
            {
              "_class": "gradientStop",
              "color": {
                "_class": "color",
                "alpha": 0.5,
                "blue": 1,
                "green": 1,
                "red": 1
              },
              "position": 0
            },
            {
              "_class": "gradientStop",
              "color": {
                "_class": "color",
                "alpha": 0.5,
                "blue": 0,
                "green": 0,
                "red": 0
              },
              "position": 1
            }
          ],
          "to": "{0.5, 1}"
        },
        "isEnabled": false,
        "noiseIndex": 0,
        "noiseIntensity": 0,
        "patternFillType": 1,
        "patternTileScale": 1
      }
    ],
    "miterLimit": 10,
    "startMarkerType": 0,
    "windingRule": 1
  },
  "windingRule": 1
}