{
  "_class": "shapeGroup",
  "booleanOperation": -1,
  "clippingMaskMode": 0,
  "do_objectID": "2085EAEE-1751-49E9-839A-496D10CB0705",
  "exportOptions": {
    "_class": "exportOptions",
    "do_objectID": "912FFC29-8679-4F01-9239-3106F596F1B2",
    "exportFormats": [
    ],
    "includedLayerIds": [
    ],
    "layerOptions": 0,
    "shouldTrim": false
  },
  "frame": {
    "_class": "rect",
    "constrainProportions": false,
    "do_objectID": "39D73617-E862-4E52-BCE5-3FB27C2F61A2",
    "height": 6.055578566938351,
    "width": 10.5146268766773,
    "x": 7.801914940370948,
    "y": 0.3730421454191705
  },
  "hasClickThrough": false,
  "hasClippingMask": false,
  "isFixedToViewport": false,
  "isFlippedHorizontal": false,
  "isFlippedVertical": false,
  "isLocked": false,
  "isVisible": true,
  "layerListExpandedType": 0,
  "layers": [
    {
      "class": "shapePath",
      "id": "ABF32FE3-62DB-4827-A7D8-3580A33F2CCA"
    }
  ],
  "name": "Path 39",
  "nameIsFixed": false,
  "resizingConstraint": 63,
  "resizingType": 0,
  "rotation": 0,
  "shouldBreakMaskChain": false,
  "style": {
    "_class": "style",
    "borderOptions": {
      "_class": "borderOptions",
      "dashPattern": [
      ],
      "do_objectID": "6E85C67A-B28C-4A0E-A9F7-FE7DCEA44A77",
      "isEnabled": false,
      "lineCapStyle": 1,
      "lineJoinStyle": 1
    },
    "borders": [
      {
        "_class": "border",
        "color": {
          "_class": "color",
          "alpha": 1,
          "blue": 0.7411764705882353,
          "green": 0.6392156862745098,
          "red": 0.6196078431372549
        },
        "fillType": 0,
        "isEnabled": true,
        "position": 0,
        "thickness": 1
      }
    ],
    "do_objectID": "EB8B33D7-F37A-4FCC-86AF-ACB84DB2206F",
    "endMarkerType": 0,
    "miterLimit": 10,
    "startMarkerType": 0,
    "windingRule": 0
  },
  "windingRule": 0
}