{
  "_class": "shapeGroup",
  "booleanOperation": 0,
  "clippingMaskMode": 0,
  "do_objectID": "E07AAD53-FD77-4DA5-B86B-1B0D8EEFCA14",
  "exportOptions": {
    "_class": "exportOptions",
    "do_objectID": "299944BA-00C5-47F5-86CD-9CBE4983C4AD",
    "exportFormats": [
    ],
    "includedLayerIds": [
    ],
    "layerOptions": 0,
    "shouldTrim": false
  },
  "frame": {
    "_class": "rect",
    "constrainProportions": false,
    "do_objectID": "2007954E-6179-4214-BB47-6492FB19755C",
    "height": 44,
    "width": 305,
    "x": 0,
    "y": 0
  },
  "hasClickThrough": false,
  "hasClippingMask": true,
  "isFixedToViewport": false,
  "isFlippedHorizontal": false,
  "isFlippedVertical": false,
  "isLocked": false,
  "isVisible": true,
  "layerListExpandedType": 0,
  "layers": [
    {
      "class": "rectangle",
      "id": "EADB59AE-F9D5-4BE9-8EFD-EB022517F22E"
    }
  ],
  "name": "Rectangle 3",
  "nameIsFixed": false,
  "resizingConstraint": 63,
  "resizingType": 0,
  "rotation": 0,
  "shouldBreakMaskChain": false,
  "style": {
    "_class": "style",
    "do_objectID": "18B1B77B-FC6D-4386-850A-1D35459C1C85",
    "endMarkerType": 0,
    "fills": [
      {
        "_class": "fill",
        "color": {
          "_class": "color",
          "alpha": 1,
          "blue": 0.8313725490196078,
          "green": 0.4196078431372549,
          "red": 0.2588235294117647
        },
        "fillType": 0,
        "isEnabled": true,
        "noiseIndex": 0,
        "noiseIntensity": 0,
        "patternFillType": 1,
        "patternTileScale": 1
      }
    ],
    "miterLimit": 10,
    "startMarkerType": 0,
    "windingRule": 1
  },
  "windingRule": 1
}