{
  "_class": "group",
  "booleanOperation": -1,
  "clippingMaskMode": 0,
  "do_objectID": "306C34FA-B48B-4A41-83D2-54B7E8AC9691",
  "exportOptions": {
    "_class": "exportOptions",
    "do_objectID": "96124ED1-5917-4927-8547-67E05B0A4336",
    "exportFormats": [
    ],
    "includedLayerIds": [
    ],
    "layerOptions": 0,
    "shouldTrim": false
  },
  "frame": {
    "_class": "rect",
    "constrainProportions": false,
    "do_objectID": "18D9585A-082E-48A6-A987-62F8C0395FCE",
    "height": 177,
    "width": 157,
    "x": 11.77734375,
    "y": 1.7578125
  },
  "hasClickThrough": false,
  "hasClippingMask": false,
  "isFixedToViewport": false,
  "isFlippedHorizontal": false,
  "isFlippedVertical": false,
  "isLocked": false,
  "isVisible": true,
  "layerListExpandedType": 1,
  "layers": [
    {
      "class": "bitmap",
      "id": "688C6AC4-624C-4503-82E2-1C2FE608881C"
    },
    {
      "class": "shapePath",
      "id": "AF9155C7-B8AF-4633-82F0-3FACAF2A1689"
    },
    {
      "class": "shapePath",
      "id": "7D6EA7F8-CA47-4337-AD75-AFE052890F96"
    },
    {
      "class": "shapePath",
      "id": "7DC58CE5-663C-4139-A26F-A93462998E5B"
    },
    {
      "class": "shapePath",
      "id": "93E5AC80-EE00-4032-8D56-1944E2133510"
    }
  ],
  "name": "分组 11",
  "nameIsFixed": false,
  "resizingConstraint": 63,
  "resizingType": 0,
  "rotation": 0,
  "shouldBreakMaskChain": false,
  "style": {
    "_class": "style",
    "do_objectID": "0DD14A60-37B5-4D3E-AF53-6DDEA16AE10E",
    "endMarkerType": 0,
    "miterLimit": 10,
    "startMarkerType": 0,
    "windingRule": 1
  }
}