{
  "_class": "shapePath",
  "booleanOperation": -1,
  "clippingMaskMode": 0,
  "do_objectID": "81261E38-7082-4FD4-99CF-F5C2EDAE2A87",
  "edited": true,
  "exportOptions": {
    "_class": "exportOptions",
    "do_objectID": "9B62582A-DAE0-4BB4-9970-F1C3C32D0473",
    "exportFormats": [
    ],
    "includedLayerIds": [
    ],
    "layerOptions": 0,
    "shouldTrim": false
  },
  "frame": {
    "_class": "rect",
    "constrainProportions": false,
    "do_objectID": "0FFF53C7-1309-437B-98C1-56734F650E29",
    "height": 6.81273408959413,
    "width": 5.031554323560158,
    "x": 119.7674456764398,
    "y": 15.9883159104059
  },
  "hasClippingMask": false,
  "isClosed": false,
  "isFixedToViewport": false,
  "isFlippedHorizontal": false,
  "isFlippedVertical": false,
  "isLocked": false,
  "isVisible": true,
  "layerListExpandedType": 0,
  "name": "Fill 25",
  "nameIsFixed": false,
  "pointRadiusBehaviour": 1,
  "points": [
    {
      "_class": "curvePoint",
      "cornerRadius": 0,
      "curveFrom": "{0.12999051217584262, 0.70753298546564725}",
      "curveMode": 4,
      "curveTo": "{0.12889741059205767, 0.71824821360165814}",
      "hasCurveFrom": true,
      "hasCurveTo": false,
      "point": "{0.12889741059205767, 0.71824821360165814}"
    },
    {
      "_class": "curvePoint",
      "cornerRadius": 0,
      "curveFrom": "{0.13376668128347569, 0.68287328235810751}",
      "curveMode": 4,
      "curveTo": "{0.13128235950214112, 0.69674436535609552}",
      "hasCurveFrom": true,
      "hasCurveTo": true,
      "point": "{0.13317044405595765, 0.68588235327301117}"
    },
    {
      "_class": "curvePoint",
      "cornerRadius": 0,
      "curveFrom": "{0.13585351157980577, 0.67171770238088435}",
      "curveMode": 4,
      "curveTo": "{0.13436291851099375, 0.67979081946966291}",
      "hasCurveFrom": true,
      "hasCurveTo": true,
      "point": "{0.13495915573852307, 0.67678174855475104}"
    },
    {
      "_class": "curvePoint",
      "cornerRadius": 0,
      "curveFrom": "{0.13883469771740725, 0.65814018727703516}",
      "curveMode": 2,
      "curveTo": "{0.13684724029233961, 0.66665365620701778}",
      "hasCurveFrom": true,
      "hasCurveTo": true,
      "point": "{0.13803971474737567, 0.66158961003314276}"
    },
    {
      "_class": "curvePoint",
      "cornerRadius": 0,
      "curveFrom": "{0.14171651098375762, 0.64639747151153448}",
      "curveMode": 4,
      "curveTo": "{0.13962968068742754, 0.65476415649445185}",
      "hasCurveFrom": true,
      "hasCurveTo": true,
      "point": "{0.14042466365745912, 0.65131473373833593}"
    },
    {
      "_class": "curvePoint",
      "cornerRadius": 0,
      "curveFrom": "{0.14509518860637488, 0.63377405206363413}",
      "curveMode": 4,
      "curveTo": "{0.14300835831005612, 0.64148020928473304}",
      "hasCurveFrom": true,
      "hasCurveTo": true,
      "point": "{0.1443002056363433, 0.63648955508439897}"
    },
    {
      "_class": "curvePoint",
      "cornerRadius": 0,
      "curveFrom": "{0.15046132365405981, 0.61571962657417922}",
      "curveMode": 4,
      "curveTo": "{0.14589017157640646, 0.63105854904286096}",
      "hasCurveFrom": true,
      "hasCurveTo": true,
      "point": "{0.14678452741767789, 0.62826965404855517}"
    },
    {
      "_class": "curvePoint",
      "cornerRadius": 0,
      "curveFrom": "{0.16000111929439362, 0.58841781241940716}",
      "curveMode": 4,
      "curveTo": "{0.15463498424670868, 0.60316959909981149}",
      "hasCurveFrom": true,
      "hasCurveTo": true,
      "point": "{0.15930550919562445, 0.59054617965190281}"
    },
    {
      "_class": "curvePoint",
      "cornerRadius": 0,
      "curveFrom": "{0.16586411869834547, 0.57337245784486413}",
      "curveMode": 2,
      "curveTo": "{0.16089547513567631, 0.58636283716044413}",
      "hasCurveFrom": true,
      "hasCurveTo": true,
      "point": "{0.1616904581057079, 0.58423446992794847}"
    },
    {
      "_class": "curvePoint",
      "cornerRadius": 0,
      "curveFrom": "{0.17550328720994166, 0.55084112196982837}",
      "curveMode": 4,
      "curveTo": "{0.17023652503350786, 0.5625104457617881}",
      "hasCurveFrom": true,
      "hasCurveTo": true,
      "point": "{0.17510579572492588, 0.55164843367870375}"
    },
    {
      "_class": "curvePoint",
      "cornerRadius": 0,
      "curveFrom": "{0.18086942225762659, 0.53873144633665626}",
      "curveMode": 4,
      "curveTo": "{0.17590077869494616, 0.55003381026094467}",
      "hasCurveFrom": true,
      "hasCurveTo": true,
      "point": "{0.17619889730871083, 0.54922649855206929}"
    },
    {
      "_class": "curvePoint",
      "cornerRadius": 0,
      "curveFrom": "{0.19289353967929496, 0.51517262283213072}",
      "curveMode": 2,
      "curveTo": "{0.1860368115628093, 0.52823639412124335}",
      "hasCurveFrom": true,
      "hasCurveTo": true,
      "point": "{0.19150231948174534, 0.51781473387937127}"
    },
    {
      "_class": "curvePoint",
      "cornerRadius": 0,
      "curveFrom": "{0.20024713215204754, 0.50108136391354485}",
      "curveMode": 2,
      "curveTo": "{0.19418538700559346, 0.5125305117848985}",
      "hasCurveFrom": true,
      "hasCurveTo": true,
      "point": "{0.19557660720314307, 0.50988840073765784}"
    },
    {
      "_class": "curvePoint",
      "cornerRadius": 0,
      "curveFrom": "{0.2109794022474287, 0.48207284276814932}",
      "curveMode": 4,
      "curveTo": "{0.20521577571472799, 0.49220093511588259}",
      "hasCurveFrom": true,
      "hasCurveTo": true,
      "point": "{0.21018441927739712, 0.48339389829176127}"
    },
    {
      "_class": "curvePoint",
      "cornerRadius": 0,
      "curveFrom": "{0.21823362184893016, 0.46966959924084684}",
      "curveMode": 4,
      "curveTo": "{0.21177438521744898, 0.48075178724452905}",
      "hasCurveFrom": true,
      "hasCurveTo": true,
      "point": "{0.21256936818748057, 0.47943073172090872}"
    },
    {
      "_class": "curvePoint",
      "cornerRadius": 0,
      "curveFrom": "{0.23045648501311208, 0.45036751020131249}",
      "curveMode": 4,
      "curveTo": "{0.22429536699539557, 0.45998185873430919}",
      "hasCurveFrom": false,
      "hasCurveTo": true,
      "point": "{0.23045648501311208, 0.45036751020131249}"
    },
    {
      "_class": "curvePoint",
      "cornerRadius": 0,
      "curveFrom": "{0.24059251788096389, 0.43524876365323684}",
      "curveMode": 4,
      "curveTo": "{0.23542512857578121, 0.44288152890081145}",
      "hasCurveFrom": true,
      "hasCurveTo": false,
      "point": "{0.23542512857578121, 0.44288152890081145}"
    },
    {
      "_class": "curvePoint",
      "cornerRadius": 0,
      "curveFrom": "{0.2527160081738834, 0.41778147395205939}",
      "curveMode": 4,
      "curveTo": "{0.2457599071861466, 0.42768939037920317}",
      "hasCurveFrom": true,
      "hasCurveTo": true,
      "point": "{0.25102666936258039, 0.42013001710516118}"
    },
    {
      "_class": "curvePoint",
      "cornerRadius": 0,
      "curveFrom": "{0.26285204104173521, 0.4037636070070062}",
      "curveMode": 4,
      "curveTo": "{0.25440534698519768, 0.41550632277249849}",
      "hasCurveFrom": true,
      "hasCurveTo": true,
      "point": "{0.25599531292524952, 0.4131577796193967}"
    },
    {
      "_class": "curvePoint",
      "cornerRadius": 0,
      "curveFrom": "{0.27855295469978553, 0.38336063836445772}",
      "curveMode": 2,
      "curveTo": "{0.26990751490073445, 0.39436943439460731}",
      "hasCurveFrom": true,
      "hasCurveTo": true,
      "point": "{0.27716173450223591, 0.38512204572928199}"
    },
    {
      "_class": "curvePoint",
      "cornerRadius": 0,
      "curveFrom": "{0.28789400459761705, 0.37183809851956318}",
      "curveMode": 4,
      "curveTo": "{0.28004354776858625, 0.38159923099963344}",
      "hasCurveFrom": true,
      "hasCurveTo": true,
      "point": "{0.28143476796613587, 0.37983782363480917}"
    },
    {
      "_class": "curvePoint",
      "cornerRadius": 0,
      "curveFrom": "{0.30319742677065153, 0.3536368890830513}",
      "curveMode": 4,
      "curveTo": "{0.29445261410034934, 0.36383837340432557}",
      "hasCurveFrom": true,
      "hasCurveTo": true,
      "point": "{0.30120996934558392, 0.35591204026261219}"
    },
    {
      "_class": "curvePoint",
      "cornerRadius": 0,
      "curveFrom": "{0.31561903567733574, 0.33932545424385102}",
      "curveMode": 4,
      "curveTo": "{0.30508551132446809, 0.35128834592994951}",
      "hasCurveFrom": true,
      "hasCurveTo": true,
      "point": "{0.30717234162078688, 0.34901319475038867}"
    },
    {
      "_class": "curvePoint",
      "cornerRadius": 0,
      "curveFrom": "{0.33430113547298751, 0.31906926954837611}",
      "curveMode": 4,
      "curveTo": "{0.32416510260513565, 0.32985788965791951}",
      "hasCurveFrom": true,
      "hasCurveTo": true,
      "point": "{0.33300928814668901, 0.32053710901906157}"
    },
    {
      "_class": "curvePoint",
      "cornerRadius": 0,
      "curveFrom": "{0.34632525289465588, 0.30659263404753268}",
      "curveMode": 3,
      "curveTo": "{0.33579172854178824, 0.31767482205122322}",
      "hasCurveFrom": true,
      "hasCurveTo": true,
      "point": "{0.33718294873933785, 0.3162069825805377}"
    },
    {
      "_class": "curvePoint",
      "cornerRadius": 0,
      "curveFrom": "{0.36689543724412416, 0.2865566252726639}",
      "curveMode": 4,
      "curveTo": "{0.35586504853498963, 0.2970516774880686}",
      "hasCurveFrom": true,
      "hasCurveTo": true,
      "point": "{0.36560358991782566, 0.28773089684921066}"
    },
    {
      "_class": "curvePoint",
      "cornerRadius": 0,
      "curveFrom": "{0.38160262218964064, 0.27246536635406976}",
      "curveMode": 3,
      "curveTo": "{0.36808791169917154, 0.28530896172257625}",
      "hasCurveFrom": true,
      "hasCurveTo": true,
      "point": "{0.36937975902545872, 0.28406129817248854}"
    },
    {
      "_class": "curvePoint",
      "cornerRadius": 0,
      "curveFrom": "{0.40863204317059015, 0.24883315087601154}",
      "curveMode": 4,
      "curveTo": "{0.3941236039675759, 0.26123639440331403}",
      "hasCurveFrom": true,
      "hasCurveTo": true,
      "point": "{0.40704207723052699, 0.25022759837316444}"
    },
    {
      "_class": "curvePoint",
      "cornerRadius": 0,
      "curveFrom": "{0.42005992336472919, 0.2391454103694739}",
      "curveMode": 4,
      "curveTo": "{0.41032138198189311, 0.24729191943178511}",
      "hasCurveFrom": true,
      "hasCurveTo": true,
      "point": "{0.41211009366445855, 0.24589747193463221}"
    },
    {
      "_class": "curvePoint",
      "cornerRadius": 0,
      "curveFrom": "{0.43665519286406218, 0.22578807118622252}",
      "curveMode": 4,
      "curveTo": "{0.42810912593626221, 0.2325401327513808}",
      "hasCurveFrom": true,
      "hasCurveTo": true,
      "point": "{0.43635707425030879, 0.22600824710682868}"
    },
    {
      "_class": "curvePoint",
      "cornerRadius": 0,
      "curveFrom": "{0.44589686989064259, 0.21844887383279502}",
      "curveMode": 4,
      "curveTo": "{0.43705268434907796, 0.22549450329208373}",
      "hasCurveFrom": true,
      "hasCurveTo": true,
      "point": "{0.43735080296284262, 0.22520093539795333}"
    },
    {
      "_class": "curvePoint",
      "cornerRadius": 0,
      "curveFrom": "{0.46537395265631465, 0.20406404702006209}",
      "curveMode": 4,
      "curveTo": "{0.45464168256094478, 0.21191698818823454}",
      "hasCurveFrom": true,
      "hasCurveTo": true,
      "point": "{0.46338649523124703, 0.20545849451721498}"
    },
    {
      "_class": "curvePoint",
      "cornerRadius": 0,
      "curveFrom": "{0.48057800195809802, 0.19312864296344512}",
      "curveMode": 4,
      "curveTo": "{0.4671626643388801, 0.20274299149644182}",
      "hasCurveFrom": true,
      "hasCurveTo": true,
      "point": "{0.46915012176394771, 0.20142193597282151}"
    },
    {
      "_class": "curvePoint",
      "cornerRadius": 0,
      "curveFrom": "{0.50502372828645059, 0.17668884089174916}",
      "curveMode": 3,
      "curveTo": "{0.49220462789475061, 0.18505552587466653}",
      "hasCurveFrom": true,
      "hasCurveTo": true,
      "point": "{0.5040299995739167, 0.17734936865355933}"
    },
    {
      "_class": "curvePoint",
      "cornerRadius": 0,
      "curveFrom": "{0.51943279461820235, 0.16736806025289125}",
      "curveMode": 4,
      "curveTo": "{0.50611682987024675, 0.17595492115640643}",
      "hasCurveFrom": true,
      "hasCurveTo": true,
      "point": "{0.5072099314540317, 0.17529439339459627}"
    },
    {
      "_class": "curvePoint",
      "cornerRadius": 0,
      "curveFrom": "{0.54685970708416765, 0.15107504212826886}",
      "curveMode": 3,
      "curveTo": "{0.53185440352488655, 0.15980868697884923}",
      "hasCurveFrom": true,
      "hasCurveTo": true,
      "point": "{0.54447475817408419, 0.15246948962542176}"
    },
    {
      "_class": "curvePoint",
      "cornerRadius": 0,
      "curveFrom": "{0.56405121381101875, 0.14131390964819859}",
      "curveMode": 3,
      "curveTo": "{0.54914528312299993, 0.14968059463111597}",
      "hasCurveFrom": true,
      "hasCurveTo": true,
      "point": "{0.55162960490433455, 0.14828614713396307}"
    },
    {
      "_class": "curvePoint",
      "cornerRadius": 0,
      "curveFrom": "{0.59147812627697272, 0.12700247480899829}",
      "curveMode": 4,
      "curveTo": "{0.57657219558895401, 0.13456184808304031}",
      "hasCurveFrom": true,
      "hasCurveTo": true,
      "point": "{0.58919255023814032, 0.12810335441201243}"
    },
    {
      "_class": "curvePoint",
      "cornerRadius": 0,
      "curveFrom": "{0.60926587023134182, 0.11826882995841791}",
      "curveMode": 3,
      "curveTo": "{0.593763702315805, 0.12597498717951677}",
      "hasCurveFrom": true,
      "hasCurveTo": true,
      "point": "{0.59594990548338622, 0.12487410757650265}"
    },
    {
      "_class": "curvePoint",
      "cornerRadius": 0,
      "curveFrom": "{0.64712693417892353, 0.10153545999258319}",
      "curveMode": 2,
      "curveTo": "{0.62268120785057102, 0.11195712023446358}",
      "hasCurveFrom": true,
      "hasCurveTo": true,
      "point": "{0.63619591834104017, 0.10623254629877846}"
    },
    {
      "_class": "curvePoint",
      "cornerRadius": 0,
      "curveFrom": "{0.67177140624977827, 0.092214679353725265}",
      "curveMode": 4,
      "curveTo": "{0.65785920427429345, 0.097352117501124505}",
      "hasCurveFrom": true,
      "hasCurveTo": true,
      "point": "{0.66869084724092565, 0.093315558956739389}"
    },
    {
      "_class": "curvePoint",
      "cornerRadius": 0,
      "curveFrom": "{0.68598172683902792, 0.087077241206317671}",
      "curveMode": 2,
      "curveTo": "{0.67475259238739105, 0.091113799750711141}",
      "hasCurveFrom": true,
      "hasCurveTo": true,
      "point": "{0.67783315139624367, 0.090012920147697004}"
    },
    {
      "_class": "curvePoint",
      "cornerRadius": 0,
      "curveFrom": "{0.70516069099094658, 0.080838923455904294}",
      "curveMode": 4,
      "curveTo": "{0.69413030228181205, 0.084361738185544488}",
      "hasCurveFrom": true,
      "hasCurveTo": true,
      "point": "{0.70227887772459618, 0.081793019111844861}"
    },
    {
      "_class": "curvePoint",
      "cornerRadius": 0,
      "curveFrom": "{0.71847665573891339, 0.076728972937978229}",
      "curveMode": 4,
      "curveTo": "{0.70794313138604581, 0.079884827799955385}",
      "hasCurveFrom": true,
      "hasCurveTo": true,
      "point": "{0.71072557178114504, 0.079077516091080033}"
    },
    {
      "_class": "curvePoint",
      "cornerRadius": 0,
      "curveFrom": "{0.73527067098074872, 0.072252062552380772}",
      "curveMode": 4,
      "curveTo": "{0.72592962108292847, 0.074673997679015183}",
      "hasCurveFrom": true,
      "hasCurveTo": true,
      "point": "{0.7333825864269321, 0.072692414393584759}"
    },
    {
      "_class": "curvePoint",
      "cornerRadius": 0,
      "curveFrom": "{0.74828851711495081, 0.068802639796264844}",
      "curveMode": 4,
      "curveTo": "{0.73715875553456522, 0.071591534790570635}",
      "hasCurveFrom": true,
      "hasCurveTo": true,
      "point": "{0.73904684008838173, 0.071151182949366648}"
    },
    {
      "_class": "curvePoint",
      "cornerRadius": 0,
      "curveFrom": "{0.77183988760203193, 0.063811985595930806}",
      "curveMode": 2,
      "curveTo": "{0.75743082127028016, 0.066747664537310153}",
      "hasCurveFrom": true,
      "hasCurveTo": true,
      "point": "{0.76657312542559819, 0.06491286519894493}"
    },
    {
      "_class": "curvePoint",
      "cornerRadius": 0,
      "curveFrom": "{0.78485773373623413, 0.061536834416369958}",
      "curveMode": 4,
      "curveTo": "{0.77700727690721461, 0.062931281913522846}",
      "hasCurveFrom": true,
      "hasCurveTo": true,
      "point": "{0.78217466621238607, 0.062050578231106539}"
    },
    {
      "_class": "curvePoint",
      "cornerRadius": 0,
      "curveFrom": "{0.79767683412793411, 0.059408467183874311}",
      "curveMode": 4,
      "curveTo": "{0.78744142838881981, 0.061023090601625023}",
      "hasCurveFrom": true,
      "hasCurveTo": true,
      "point": "{0.78992575017016575, 0.06065613073395365}"
    },
    {
      "_class": "curvePoint",
      "cornerRadius": 0,
      "curveFrom": "{0.8247062551088723, 0.056179220348364547}",
      "curveMode": 2,
      "curveTo": "{0.80552729095695363, 0.058307587580860187}",
      "hasCurveFrom": true,
      "hasCurveTo": true,
      "point": "{0.81307962917221976, 0.057500275871976488}"
    },
    {
      "_class": "curvePoint",
      "cornerRadius": 0,
      "curveFrom": "{0.84945010005098942, 0.05485816482474426}",
      "curveMode": 2,
      "curveTo": "{0.83593538956052038, 0.055371908639480848}",
      "hasCurveFrom": true,
      "hasCurveTo": true,
      "point": "{0.84726389688341952, 0.054931556798276868}"
    },
    {
      "_class": "curvePoint",
      "cornerRadius": 0,
      "curveFrom": "{0.86395853925400368, 0.05441781298354028}",
      "curveMode": 2,
      "curveTo": "{0.85173567608982181, 0.054711380877670704}",
      "hasCurveFrom": true,
      "hasCurveTo": true,
      "point": "{0.8540212521286541, 0.054637988904138096}"
    },
    {
      "_class": "curvePoint",
      "cornerRadius": 0,
      "curveFrom": "{0.88522433370224118, 0.054931556798276868}",
      "curveMode": 2,
      "curveTo": "{0.87389582637934193, 0.05441781298354028}",
      "hasCurveFrom": true,
      "hasCurveTo": true,
      "point": "{0.88363436776218929, 0.05485816482474426}"
    },
    {
      "_class": "curvePoint",
      "cornerRadius": 0,
      "curveFrom": "{0.89645346815388927, 0.055592084560087004}",
      "curveMode": 4,
      "curveTo": "{0.88691367251355546, 0.055078340745350424}",
      "hasCurveFrom": true,
      "hasCurveTo": true,
      "point": "{0.88870238419610958, 0.055151732718883024}"
    },
    {
      "_class": "curvePoint",
      "cornerRadius": 0,
      "curveFrom": "{0.91404246636574482, 0.05742688389844388}",
      "curveMode": 4,
      "curveTo": "{0.90420455211165762, 0.056252612321897148}",
      "hasCurveFrom": true,
      "hasCurveTo": true,
      "point": "{0.91175689032692375, 0.057206707977846064}"
    },
    {
      "_class": "curvePoint",
      "cornerRadius": 0,
      "curveFrom": "{0.9274578039849628, 0.059261683236800755}",
      "curveMode": 4,
      "curveTo": "{0.91642741527582827, 0.057720451792582651}",
      "hasCurveFrom": true,
      "hasCurveTo": true,
      "point": "{0.91871299131466055, 0.058014019686721416}"
    },
    {
      "_class": "curvePoint",
      "cornerRadius": 0,
      "curveFrom": "{0.94474868358307618, 0.062417538098777918}",
      "curveMode": 4,
      "curveTo": "{0.93600387091276271, 0.060582738760421043}",
      "hasCurveFrom": true,
      "hasCurveTo": true,
      "point": "{0.94425181922680934, 0.06234414612524531}"
    },
    {
      "_class": "curvePoint",
      "cornerRadius": 0,
      "curveFrom": "{0.9532947505108762, 0.064399121384208349}",
      "curveMode": 4,
      "curveTo": "{0.94504680219682957, 0.062564322045851467}",
      "hasCurveFrom": true,
      "hasCurveTo": true,
      "point": "{0.94544429368184535, 0.062637714019384075}"
    },
    {
      "_class": "curvePoint",
      "cornerRadius": 0,
      "curveFrom": "{0.97068500298022953, 0.06931638361100978}",
      "curveMode": 2,
      "curveTo": "{0.96094646159739339, 0.066454096643171381}",
      "hasCurveFrom": true,
      "hasCurveTo": true,
      "point": "{0.96839942694139713, 0.068655855849199629}"
    },
    {
      "_class": "curvePoint",
      "cornerRadius": 0,
      "curveFrom": "{0.98141727307559934, 0.072765806367125707}",
      "curveMode": 2,
      "curveTo": "{0.97277183327654826, 0.069976911372819917}",
      "hasCurveFrom": true,
      "hasCurveTo": true,
      "point": "{0.97505740931538054, 0.070710831108162675}"
    },
    {
      "_class": "curvePoint",
      "cornerRadius": 0,
      "curveFrom": "{0.9959257122786136, 0.078343596355728934}",
      "curveMode": 4,
      "curveTo": "{0.98777713683582935, 0.075040957546686562}",
      "hasCurveFrom": true,
      "hasCurveTo": true,
      "point": "{0.99383888198228354, 0.077536284646853582}"
    },
    {
      "_class": "curvePoint",
      "cornerRadius": 0,
      "curveFrom": "{1, 0.079884827799955385}",
      "curveMode": 4,
      "curveTo": "{0.99791316970368127, 0.079077516091080033}",
      "hasCurveFrom": false,
      "hasCurveTo": true,
      "point": "{1, 0.079884827799955385}"
    },
    {
      "_class": "curvePoint",
      "cornerRadius": 0,
      "curveFrom": "{0.87210711469678781, 0.024987631596264308}",
      "curveMode": 4,
      "curveTo": "{0.87300147053807053, 0.025427983437468292}",
      "hasCurveFrom": true,
      "hasCurveTo": false,
      "point": "{0.87300147053807053, 0.025427983437468292}"
    },
    {
      "_class": "curvePoint",
      "cornerRadius": 0,
      "curveFrom": "{0.86912592855917503, 0.02381336001971758}",
      "curveMode": 4,
      "curveTo": "{0.8712127588555052, 0.024620671728592936}",
      "hasCurveFrom": true,
      "hasCurveTo": true,
      "point": "{0.87021903014297131, 0.024180319887388953}"
    },
    {
      "_class": "curvePoint",
      "cornerRadius": 0,
      "curveFrom": "{0.86077860737388867, 0.020584113184207813}",
      "curveMode": 4,
      "curveTo": "{0.86793345410413902, 0.023446400152046205}",
      "hasCurveFrom": true,
      "hasCurveTo": true,
      "point": "{0.86693972539160513, 0.023006048310842225}"
    },
    {
      "_class": "curvePoint",
      "cornerRadius": 0,
      "curveFrom": "{0.84686640539840374, 0.015813634904471595}",
      "curveMode": 4,
      "curveTo": "{0.85451811648492104, 0.018308962004638614}",
      "hasCurveFrom": true,
      "hasCurveTo": true,
      "point": "{0.84805887985343986, 0.016253986745675575}"
    },
    {
      "_class": "curvePoint",
      "cornerRadius": 0,
      "curveFrom": "{0.84348772777578651, 0.014639363327924865}",
      "curveMode": 4,
      "curveTo": "{0.84577330381461879, 0.015299891089735009}",
      "hasCurveFrom": true,
      "hasCurveTo": true,
      "point": "{0.84458082935957146, 0.014932931222063633}"
    },
    {
      "_class": "curvePoint",
      "cornerRadius": 0,
      "curveFrom": "{0.83404730500670388, 0.011923860307151686}",
      "curveMode": 2,
      "curveTo": "{0.84249399906325262, 0.014492579380851309}",
      "hasCurveFrom": true,
      "hasCurveTo": true,
      "point": "{0.84150027035071884, 0.014199011486720883}"
    },
    {
      "_class": "curvePoint",
      "cornerRadius": 0,
      "curveFrom": "{0.81824701847740244, 0.0081074776833643808}",
      "curveMode": 4,
      "curveTo": "{0.82639559392018658, 0.0098688850481886484}",
      "hasCurveFrom": true,
      "hasCurveTo": true,
      "point": "{0.81844576421990467, 0.0081808696569053308}"
    },
    {
      "_class": "curvePoint",
      "cornerRadius": 0,
      "curveFrom": "{0.81755140837862195, 0.0078873017627665611}",
      "curveMode": 4,
      "curveTo": "{0.81794889986363772, 0.0079606937362991688}",
      "hasCurveFrom": false,
      "hasCurveTo": true,
      "point": "{0.81755140837862195, 0.0078873017627665611}"
    },
    {
      "_class": "curvePoint",
      "cornerRadius": 0,
      "curveFrom": "{0.80910471432208442, 0.0061258943979422935}",
      "curveMode": 4,
      "curveTo": "{0.81735266263611972, 0.0078873017627665611}",
      "hasCurveFrom": true,
      "hasCurveTo": false,
      "point": "{0.81735266263611972, 0.0078873017627665611}"
    },
    {
      "_class": "curvePoint",
      "cornerRadius": 0,
      "curveFrom": "{0.79082010601143715, 0.0034103913771691141}",
      "curveMode": 4,
      "curveTo": "{0.8005586473942844, 0.0047314469007894008}",
      "hasCurveFrom": true,
      "hasCurveTo": true,
      "point": "{0.79181383472398226, 0.0035571753242426701}"
    },
    {
      "_class": "curvePoint",
      "cornerRadius": 0,
      "curveFrom": "{0.7875408012600823, 0.0028232555888915768}",
      "curveMode": 2,
      "curveTo": "{0.78982637729890326, 0.0031902154565629517}",
      "hasCurveFrom": true,
      "hasCurveTo": true,
      "point": "{0.78893202145763186, 0.0030434315094977392}"
    },
    {
      "_class": "curvePoint",
      "cornerRadius": 0,
      "curveFrom": "{0.77720602264971694, 0.0017957679594100585}",
      "curveMode": 2,
      "curveTo": "{0.78605020819128157, 0.0028232555888915768}",
      "hasCurveFrom": true,
      "hasCurveTo": true,
      "point": "{0.78485773373623413, 0.0026764716418263643}"
    },
    {
      "_class": "curvePoint",
      "cornerRadius": 0,
      "curveFrom": "{0.76041200740788162, 0.00062149638286332777}",
      "curveMode": 2,
      "curveTo": "{0.76945493869194848, 0.0011352401976082588}",
      "hasCurveFrom": true,
      "hasCurveTo": true,
      "point": "{0.76160448186291774, 0.00069488835639593398}"
    },
    {
      "_class": "curvePoint",
      "cornerRadius": 0,
      "curveFrom": "{0.75753019414153133, 0.0003279284887245592}",
      "curveMode": 4,
      "curveTo": "{0.75921953295283429, 0.00040132046226550911}",
      "hasCurveFrom": true,
      "hasCurveTo": true,
      "point": "{0.75792768562654711, 0.00040132046226550911}"
    },
    {
      "_class": "curvePoint",
      "cornerRadius": 0,
      "curveFrom": "{0.74699666978866364, -3.9031378946815651e-05}",
      "curveMode": 4,
      "curveTo": "{0.75703332978526439, 0.00040132046226550911}",
      "hasCurveFrom": true,
      "hasCurveTo": true,
      "point": "{0.75663583830024861, 0.0003279284887245592}"
    },
    {
      "_class": "curvePoint",
      "cornerRadius": 0,
      "curveFrom": "{0.72602899395417952, 0.00018114454165934671}",
      "curveMode": 4,
      "curveTo": "{0.73705938266331406, -0.00011242335247942188}",
      "hasCurveFrom": true,
      "hasCurveTo": true,
      "point": "{0.72712209553796447, 0.00018114454165934671}"
    },
    {
      "_class": "curvePoint",
      "cornerRadius": 0,
      "curveFrom": "{0.72294843494531569, 0.00018114454165934671}",
      "curveMode": 4,
      "curveTo": "{0.7251346381128968, 0.0001077525681267405}",
      "hasCurveFrom": true,
      "hasCurveTo": true,
      "point": "{0.72414090940036302, 0.00018114454165934671}"
    },
    {
      "_class": "curvePoint",
      "cornerRadius": 0,
      "curveFrom": "{0.70903623296983076, 0.00091506427700209633}",
      "curveMode": 4,
      "curveTo": "{0.72155721474777734, 0.00040132046226550911}",
      "hasCurveFrom": true,
      "hasCurveTo": true,
      "point": "{0.72026536742147884, 0.00047471243579811533}"
    },
    {
      "_class": "curvePoint",
      "cornerRadius": 0,
      "curveFrom": "{0.68608109971027897, 0.0029700395359651328}",
      "curveMode": 4,
      "curveTo": "{0.697807098518194, 0.0016489840123448461}",
      "hasCurveFrom": false,
      "hasCurveTo": true,
      "point": "{0.68608109971027897, 0.0029700395359651328}"
    },
    {
      "_class": "curvePoint",
      "cornerRadius": 0,
      "curveFrom": "{0.67842938862376179, 0.003850743218373095}",
      "curveMode": 4,
      "curveTo": "{0.68598172683902792, 0.0029700395359651328}",
      "hasCurveFrom": true,
      "hasCurveTo": false,
      "point": "{0.68598172683902792, 0.0029700395359651328}"
    },
    {
      "_class": "curvePoint",
      "cornerRadius": 0,
      "curveFrom": "{0.66054227179814151, 0.0065662462391462752}",
      "curveMode": 4,
      "curveTo": "{0.67077767753724449, 0.0049516228213872197}",
      "hasCurveFrom": true,
      "hasCurveTo": true,
      "point": "{0.66302659357947613, 0.0061258943979422935}"
    },
    {
      "_class": "curvePoint",
      "cornerRadius": 0,
      "curveFrom": "{0.6507043575440431, 0.0083276536039705428}",
      "curveMode": 2,
      "curveTo": "{0.65795857714554451, 0.0070799900538828621}",
      "hasCurveFrom": true,
      "hasCurveTo": true,
      "point": "{0.65547425536421, 0.007520341895095187}"
    },
    {
      "_class": "curvePoint",
      "cornerRadius": 0,
      "curveFrom": "{0.64056832467619129, 0.010162452942327416}",
      "curveMode": 4,
      "curveTo": "{0.6459344597238762, 0.0091349653128458986}",
      "hasCurveFrom": true,
      "hasCurveTo": true,
      "point": "{0.64106518903245813, 0.01008906096879481}"
    },
    {
      "_class": "curvePoint",
      "cornerRadius": 0,
      "curveFrom": "{0.63053166467959054, 0.012217428201290454}",
      "curveMode": 4,
      "curveTo": "{0.6401708331911754, 0.010309236889400972}",
      "hasCurveFrom": true,
      "hasCurveTo": true,
      "point": "{0.63967396883490857, 0.01038262886293358}"
    },
    {
      "_class": "curvePoint",
      "cornerRadius": 0,
      "curveFrom": "{0.61025959894388693, 0.017134690428091882}",
      "curveMode": 2,
      "curveTo": "{0.62128998765302146, 0.014345795433786097}",
      "hasCurveFrom": true,
      "hasCurveTo": true,
      "point": "{0.61204831062644105, 0.016694338586887902}"
    },
    {
      "_class": "curvePoint",
      "cornerRadius": 0,
      "curveFrom": "{0.59903046449223885, 0.020143761342995486}",
      "curveMode": 4,
      "curveTo": "{0.60837151439007031, 0.017721826216369418}",
      "hasCurveFrom": true,
      "hasCurveTo": true,
      "point": "{0.60658280270750498, 0.018162178057573402}"
    },
    {
      "_class": "curvePoint",
      "cornerRadius": 0,
      "curveFrom": "{0.58283268647792164, 0.024914239622731704}",
      "curveMode": 4,
      "curveTo": "{0.59147812627697272, 0.022272128575499473}",
      "hasCurveFrom": true,
      "hasCurveTo": true,
      "point": "{0.58382641519045542, 0.024547279755060328}"
    },
    {
      "_class": "curvePoint",
      "cornerRadius": 0,
      "curveFrom": "{0.57905651737028851, 0.02594172725221322}",
      "curveMode": 4,
      "curveTo": "{0.58193833063663891, 0.025134415543337865}",
      "hasCurveFrom": true,
      "hasCurveTo": true,
      "point": "{0.58094460192410502, 0.025427983437468292}"
    },
    {
      "_class": "curvePoint",
      "cornerRadius": 0,
      "curveFrom": "{0.56723114569112243, 0.029831501849533131}",
      "curveMode": 4,
      "curveTo": "{0.57716843281647201, 0.026749038961088576}",
      "hasCurveFrom": true,
      "hasCurveTo": true,
      "point": "{0.57528034826265551, 0.027262782775833508}"
    },
    {
      "_class": "curvePoint",
      "cornerRadius": 0,
      "curveFrom": "{0.54785343579670143, 0.036583563414691433}",
      "curveMode": 2,
      "curveTo": "{0.5590825702483383, 0.032620396843838918}",
      "hasCurveFrom": true,
      "hasCurveTo": true,
      "point": "{0.55093399480555405, 0.03548268381167731}"
    },
    {
      "_class": "curvePoint",
      "cornerRadius": 0,
      "curveFrom": "{0.53096004768361516, 0.042821881165113151}",
      "curveMode": 2,
      "curveTo": "{0.54487224965909997, 0.037684443017705557}",
      "hasCurveFrom": true,
      "hasCurveTo": true,
      "point": "{0.54169231777898497, 0.038858714594260636}"
    },
    {
      "_class": "curvePoint",
      "cornerRadius": 0,
      "curveFrom": "{0.49568267838863034, 0.057500275871976488}",
      "curveMode": 2,
      "curveTo": "{0.52022777758823391, 0.047078615630104438}",
      "hasCurveFrom": true,
      "hasCurveTo": true,
      "point": "{0.50929676175035055, 0.051702309962767097}"
    },
    {
      "_class": "curvePoint",
      "cornerRadius": 0,
      "curveFrom": "{0.46676517285386426, 0.07144475084350542}",
      "curveMode": 4,
      "curveTo": "{0.48236671364066347, 0.063811985595930806}",
      "hasCurveFrom": true,
      "hasCurveTo": true,
      "point": "{0.46915012176394771, 0.070343871240491296}"
    },
    {
      "_class": "curvePoint",
      "cornerRadius": 0,
      "curveFrom": "{0.44967303899826438, 0.080031611747020601}",
      "curveMode": 4,
      "curveTo": "{0.46457896968629436, 0.072545630446519543}",
      "hasCurveFrom": true,
      "hasCurveTo": true,
      "point": "{0.46219402077621091, 0.073646510049533667}"
    },
    {
      "_class": "curvePoint",
      "cornerRadius": 0,
      "curveFrom": "{0.42224612653231036, 0.095223750268628865}",
      "curveMode": 3,
      "curveTo": "{0.43715205722032907, 0.086783673312178899}",
      "hasCurveFrom": true,
      "hasCurveTo": true,
      "point": "{0.42473044831364493, 0.09382930277147597}"
    },
    {
      "_class": "curvePoint",
      "cornerRadius": 0,
      "curveFrom": "{0.40485587406295709, 0.10527845064283789}",
      "curveMode": 3,
      "curveTo": "{0.41986117762222691, 0.09661819776578176}",
      "hasCurveFrom": true,
      "hasCurveTo": true,
      "point": "{0.41747622871214346, 0.098012645262934656}"
    },
    {
      "_class": "curvePoint",
      "cornerRadius": 0,
      "curveFrom": "{0.37921767327955719, 0.12149807679392767}",
      "curveMode": 4,
      "curveTo": "{0.39243426515627294, 0.11283782391687154}",
      "hasCurveFrom": true,
      "hasCurveTo": true,
      "point": "{0.38021140199209102, 0.12076415705858493}"
    },
    {
      "_class": "curvePoint",
      "cornerRadius": 0,
      "curveFrom": "{0.3652060984328212, 0.13059868151218779}",
      "curveMode": 4,
      "curveTo": "{0.37812457169577224, 0.12215860455573781}",
      "hasCurveFrom": true,
      "hasCurveTo": true,
      "point": "{0.37703147011197602, 0.12289252429108057}"
    },
    {
      "_class": "curvePoint",
      "cornerRadius": 0,
      "curveFrom": "{0.34105849071822203, 0.14777240331921812}",
      "curveMode": 4,
      "curveTo": "{0.35367884536740846, 0.13867179860095802}",
      "hasCurveFrom": true,
      "hasCurveTo": true,
      "point": "{0.34215159230200698, 0.14689169963681017}"
    },
    {
      "_class": "curvePoint",
      "cornerRadius": 0,
      "curveFrom": "{0.33797793170936946, 0.14982737857818118}",
      "curveMode": 2,
      "curveTo": "{0.33976664339192353, 0.14850632305456088}",
      "hasCurveFrom": true,
      "hasCurveTo": true,
      "point": "{0.33857416893688747, 0.14938702673697718}"
    },
    {
      "_class": "curvePoint",
      "cornerRadius": 0,
      "curveFrom": "{0.32774252597025522, 0.15738675185221482}",
      "curveMode": 2,
      "curveTo": "{0.33728232161058896, 0.1504145143664587}",
      "hasCurveFrom": true,
      "hasCurveTo": true,
      "point": "{0.33648733864056868, 0.15100165015472791}"
    },
    {
      "_class": "curvePoint",
      "cornerRadius": 0,
      "curveFrom": "{0.30995478201588611, 0.17103765892960499}",
      "curveMode": 4,
      "curveTo": "{0.31899771329995297, 0.16399202947030792}",
      "hasCurveFrom": true,
      "hasCurveTo": true,
      "point": "{0.310451646372153, 0.17074409103546623}"
    },
    {
      "_class": "curvePoint",
      "cornerRadius": 0,
      "curveFrom": "{0.30101122360307037, 0.17815668036243468}",
      "curveMode": 4,
      "curveTo": "{0.30955729053087033, 0.17133122682374377}",
      "hasCurveFrom": true,
      "hasCurveTo": true,
      "point": "{0.30915979904585456, 0.17169818669141512}"
    },
    {
      "_class": "curvePoint",
      "cornerRadius": 0,
      "curveFrom": "{0.28511156420251782, 0.19144062757215347}",
      "curveMode": 4,
      "curveTo": "{0.29296202103153729, 0.18468856600699515}",
      "hasCurveFrom": false,
      "hasCurveTo": true,
      "point": "{0.28511156420251782, 0.19144062757215347}"
    },
    {
      "_class": "curvePoint",
      "cornerRadius": 0,
      "curveFrom": "{0.28183225945115165, 0.19408273861938569}",
      "curveMode": 4,
      "curveTo": "{0.28282598816368548, 0.19327542691051033}",
      "hasCurveFrom": true,
      "hasCurveTo": false,
      "point": "{0.28282598816368548, 0.19327542691051033}"
    },
    {
      "_class": "curvePoint",
      "cornerRadius": 0,
      "curveFrom": "{0.2672244473768976, 0.20677955004082693}",
      "curveMode": 4,
      "curveTo": "{0.28093790360986898, 0.19496344230180199}",
      "hasCurveFrom": true,
      "hasCurveTo": true,
      "point": "{0.28004354776858625, 0.19577075401067734}"
    },
    {
      "_class": "curvePoint",
      "cornerRadius": 0,
      "curveFrom": "{0.24208311094976465, 0.22989802170414858}",
      "curveMode": 4,
      "curveTo": "{0.25470346559895102, 0.21800852199158269}",
      "hasCurveFrom": true,
      "hasCurveTo": true,
      "point": "{0.24248060243478042, 0.22960445381000982}"
    },
    {
      "_class": "curvePoint",
      "cornerRadius": 0,
      "curveFrom": "{0.24039377213845037, 0.23143925314836669}",
      "curveMode": 4,
      "curveTo": "{0.24178499233599998, 0.23026498157181996}",
      "hasCurveFrom": true,
      "hasCurveTo": true,
      "point": "{0.24138750085098418, 0.23055854946595872}"
    },
    {
      "_class": "curvePoint",
      "cornerRadius": 0,
      "curveFrom": "{0.22896589194430003, 0.24259483312558983}",
      "curveMode": 4,
      "curveTo": "{0.23959878916843008, 0.23239334880431559}",
      "hasCurveFrom": true,
      "hasCurveTo": true,
      "point": "{0.23860506045589625, 0.23327405248673191}"
    },
    {
      "_class": "curvePoint",
      "cornerRadius": 0,
      "curveFrom": "{0.20929006343611442, 0.26270423387399955}",
      "curveMode": 3,
      "curveTo": "{0.21942609630396626, 0.25206239771152134}",
      "hasCurveFrom": true,
      "hasCurveTo": true,
      "point": "{0.21018441927739712, 0.2617501382180506}"
    },
    {
      "_class": "curvePoint",
      "cornerRadius": 0,
      "curveFrom": "{0.20690511452603097, 0.26505277702710134}",
      "curveMode": 4,
      "curveTo": "{0.20829633472358058, 0.26365832952994844}",
      "hasCurveFrom": true,
      "hasCurveTo": true,
      "point": "{0.20730260601104677, 0.26461242518588901}"
    },
    {
      "_class": "curvePoint",
      "cornerRadius": 0,
      "curveFrom": "{0.19716657314319494, 0.27532765332190817}",
      "curveMode": 4,
      "curveTo": "{0.20650762304101519, 0.26556652084183791}",
      "hasCurveFrom": true,
      "hasCurveTo": true,
      "point": "{0.20601075868474827, 0.26600687268304191}"
    },
    {
      "_class": "curvePoint",
      "cornerRadius": 0,
      "curveFrom": "{0.17947820206007697, 0.29543705407031789}",
      "curveMode": 4,
      "curveTo": "{0.18871987908664611, 0.28486860988137225}",
      "hasCurveFrom": true,
      "hasCurveTo": true,
      "point": "{0.18027318503010856, 0.29448295841436894}"
    },
    {
      "_class": "curvePoint",
      "cornerRadius": 0,
      "curveFrom": "{0.17649701592247549, 0.29859290893229501}",
      "curveMode": 4,
      "curveTo": "{0.17858384621879428, 0.29631775775272584}",
      "hasCurveFrom": true,
      "hasCurveTo": true,
      "point": "{0.1777888632487627, 0.29727185340867474}"
    },
    {
      "_class": "curvePoint",
      "cornerRadius": 0,
      "curveFrom": "{0.16755345750965975, 0.30938152904183847}",
      "curveMode": 2,
      "curveTo": "{0.17550328720994166, 0.30006074840298053}",
      "hasCurveFrom": true,
      "hasCurveTo": true,
      "point": "{0.1743108127548943, 0.30145519590013342}"
    },
    {
      "_class": "curvePoint",
      "cornerRadius": 0,
      "curveFrom": "{0.1534425097916613, 0.32670203479594234}",
      "curveMode": 4,
      "curveTo": "{0.16089547513567631, 0.31738125415708446}",
      "hasCurveFrom": true,
      "hasCurveTo": true,
      "point": "{0.15443623850419513, 0.3253809792723304}"
    },
    {
      "_class": "curvePoint",
      "cornerRadius": 0,
      "curveFrom": "{0.15105756088157787, 0.3296377137373217}",
      "curveMode": 4,
      "curveTo": "{0.15234940820787635, 0.32787630637249743}",
      "hasCurveFrom": true,
      "hasCurveTo": true,
      "point": "{0.15135567949534254, 0.32919736189610938}"
    },
    {
      "_class": "curvePoint",
      "cornerRadius": 0,
      "curveFrom": "{0.14300835831005612, 0.33991259003212854}",
      "curveMode": 4,
      "curveTo": "{0.15066006939657337, 0.33015145755205827}",
      "hasCurveFrom": true,
      "hasCurveTo": true,
      "point": "{0.15026257791155759, 0.33059180939326227}"
    },
    {
      "_class": "curvePoint",
      "cornerRadius": 0,
      "curveFrom": "{0.12909615633455993, 0.35870093525691793}",
      "curveMode": 4,
      "curveTo": "{0.13585351157980577, 0.34923337067098648}",
      "hasCurveFrom": false,
      "hasCurveTo": true,
      "point": "{0.12909615633455993, 0.35870093525691793}"
    },
    {
      "_class": "curvePoint",
      "cornerRadius": 0,
      "curveFrom": "{0.12631371593947199, 0.36251731788070524}",
      "curveMode": 4,
      "curveTo": "{0.1273074446520058, 0.36097608643647883}",
      "hasCurveFrom": true,
      "hasCurveTo": false,
      "point": "{0.1273074446520058, 0.36097608643647883}"
    },
    {
      "_class": "curvePoint",
      "cornerRadius": 0,
      "curveFrom": "{0.11876137772420585, 0.37315915404318345}",
      "curveMode": 4,
      "curveTo": "{0.12531998722693816, 0.36405854932492338}",
      "hasCurveFrom": true,
      "hasCurveTo": true,
      "point": "{0.12412751277189078, 0.36559978076914984}"
    },
    {
      "_class": "curvePoint",
      "cornerRadius": 0,
      "curveFrom": "{0.10753224327255778, 0.38996591598255081}",
      "curveMode": 4,
      "curveTo": "{0.11359398841902317, 0.38071852731721711}",
      "hasCurveFrom": true,
      "hasCurveTo": true,
      "point": "{0.1085259719850916, 0.38835129256479173}"
    },
    {
      "_class": "curvePoint",
      "cornerRadius": 0,
      "curveFrom": "{0.10474980287745854, 0.39400247452693593}",
      "curveMode": 4,
      "curveTo": "{0.1063397688175217, 0.3915071474267689}",
      "hasCurveFrom": true,
      "hasCurveTo": true,
      "point": "{0.10534604010498788, 0.39304837887098704}"
    },
    {
      "_class": "curvePoint",
      "cornerRadius": 0,
      "curveFrom": "{0.097396210404705946, 0.40552501437183042}",
      "curveMode": 4,
      "curveTo": "{0.10415356564994051, 0.39495657018288483}",
      "hasCurveFrom": true,
      "hasCurveTo": true,
      "point": "{0.10355732842242246, 0.39591066583882539}"
    },
    {
      "_class": "curvePoint",
      "cornerRadius": 0,
      "curveFrom": "{0.08547146585428872, 0.42526745525256876}",
      "curveMode": 4,
      "curveTo": "{0.091334465258240558, 0.41521275487835974}",
      "hasCurveFrom": true,
      "hasCurveTo": true,
      "point": "{0.085570838725539847, 0.42490049538489738}"
    },
    {
      "_class": "curvePoint",
      "cornerRadius": 0,
      "curveFrom": "{0.084477737141754883, 0.42688207867031946}",
      "curveMode": 4,
      "curveTo": "{0.085272720111786465, 0.42556102314669919}",
      "hasCurveFrom": true,
      "hasCurveTo": true,
      "point": "{0.085073974369272928, 0.42585459104083795}"
    },
    {
      "_class": "curvePoint",
      "cornerRadius": 0,
      "curveFrom": "{0.078217246252787254, 0.43774409075340387}",
      "curveMode": 4,
      "curveTo": "{0.083980872785487978, 0.42783617432626836}",
      "hasCurveFrom": true,
      "hasCurveTo": true,
      "point": "{0.083285262686718819, 0.4289370539292825}"
    },
    {
      "_class": "curvePoint",
      "cornerRadius": 0,
      "curveFrom": "{0.067882467642421881, 0.45682600387233202}",
      "curveMode": 4,
      "curveTo": "{0.073248602690118111, 0.44655112757752519}",
      "hasCurveFrom": true,
      "hasCurveTo": true,
      "point": "{0.068677450612453464, 0.45543155637517913}"
    },
    {
      "_class": "curvePoint",
      "cornerRadius": 0,
      "curveFrom": "{0.065596891603600854, 0.46086256241672552}",
      "curveMode": 4,
      "curveTo": "{0.066988111801139172, 0.45829384334301754}",
      "hasCurveFrom": true,
      "hasCurveTo": true,
      "point": "{0.066292501702370013, 0.45968829084017043}"
    },
    {
      "_class": "curvePoint",
      "cornerRadius": 0,
      "curveFrom": "{0.059137654972119674, 0.47370615778523195}",
      "curveMode": 4,
      "curveTo": "{0.065100027247322639, 0.46211022596680484}",
      "hasCurveFrom": true,
      "hasCurveTo": true,
      "point": "{0.064603162891055735, 0.46328449754335155}"
    },
    {
      "_class": "curvePoint",
      "cornerRadius": 0,
      "curveFrom": "{0.049100994975518973, 0.49491643813665576}",
      "curveMode": 4,
      "curveTo": "{0.053970265666936988, 0.48420121000064498}",
      "hasCurveFrom": true,
      "hasCurveTo": true,
      "point": "{0.0492003678467701, 0.49476965418959057}"
    },
    {
      "_class": "curvePoint",
      "cornerRadius": 0,
      "curveFrom": "{0.048604130619252062, 0.49594392576613727}",
      "curveMode": 4,
      "curveTo": "{0.049001622104267853, 0.49513661405726195}",
      "hasCurveFrom": true,
      "hasCurveTo": true,
      "point": "{0.048902249233016726, 0.49535678997785976}"
    },
    {
      "_class": "curvePoint",
      "cornerRadius": 0,
      "curveFrom": "{0.043337368442818248, 0.508053601399301}",
      "curveMode": 4,
      "curveTo": "{0.048405384876749814, 0.49660445352794746}",
      "hasCurveFrom": true,
      "hasCurveTo": true,
      "point": "{0.04820663913423627, 0.49719158931622498}"
    },
    {
      "_class": "curvePoint",
      "cornerRadius": 0,
      "curveFrom": "{0.034195064287500257, 0.53109868108909009}",
      "curveMode": 4,
      "curveTo": "{0.038964962107667145, 0.51891561348238535}",
      "hasCurveFrom": true,
      "hasCurveTo": true,
      "point": "{0.034791301515018289, 0.52977762556546981}"
    },
    {
      "_class": "curvePoint",
      "cornerRadius": 0,
      "curveFrom": "{0.032803844089950636, 0.53454810384519769}",
      "curveMode": 4,
      "curveTo": "{0.033598827059982218, 0.53241973661270203}",
      "hasCurveFrom": true,
      "hasCurveTo": true,
      "point": "{0.033101962703704003, 0.53381418410985493}"
    },
    {
      "_class": "curvePoint",
      "cornerRadius": 0,
      "curveFrom": "{0.02763645478476795, 0.54863936276379177}",
      "curveMode": 4,
      "curveTo": "{0.032605098347437092, 0.53528202358054033}",
      "hasCurveFrom": true,
      "hasCurveTo": true,
      "point": "{0.032306979733683724, 0.53601594331589153}"
    },
    {
      "_class": "curvePoint",
      "cornerRadius": 0,
      "curveFrom": "{0.019785997955748449, 0.57381280968607651}",
      "curveMode": 4,
      "curveTo": "{0.023462794192119094, 0.56126278221170045}",
      "hasCurveFrom": false,
      "hasCurveTo": true,
      "point": "{0.019785997955748449, 0.57381280968607651}"
    },
    {
      "_class": "curvePoint",
      "cornerRadius": 0,
      "curveFrom": "{0.018196032015685284, 0.57880346388641046}",
      "curveMode": 4,
      "curveTo": "{0.018692896371952199, 0.57711544849511887}",
      "hasCurveFrom": true,
      "hasCurveTo": false,
      "point": "{0.018692896371952199, 0.57711544849511887}"
    },
    {
      "_class": "curvePoint",
      "cornerRadius": 0,
      "curveFrom": "{0.016009828848115384, 0.58694997294872164}",
      "curveMode": 4,
      "curveTo": "{0.017897913401931916, 0.58041808730416122}",
      "hasCurveFrom": true,
      "hasCurveTo": true,
      "point": "{0.017401049045665001, 0.58203271072192031}"
    },
    {
      "_class": "curvePoint",
      "cornerRadius": 0,
      "curveFrom": "{0.01273052409674923, 0.60023392015844046}",
      "curveMode": 4,
      "curveTo": "{0.01481735439306801, 0.59186723517552309}",
      "hasCurveFrom": true,
      "hasCurveTo": true,
      "point": "{0.013525507066780813, 0.59685788937585715}"
    },
    {
      "_class": "curvePoint",
      "cornerRadius": 0,
      "curveFrom": "{0.0099480837016499932, 0.61219681184453068}",
      "curveMode": 4,
      "curveTo": "{0.011836168255466526, 0.60368334291454806}",
      "hasCurveFrom": true,
      "hasCurveTo": true,
      "point": "{0.011041185285434943, 0.60705937369713137}"
    },
    {
      "_class": "curvePoint",
      "cornerRadius": 0,
      "curveFrom": "{0.0074637619203154221, 0.62474683931890662}",
      "curveMode": 2,
      "curveTo": "{0.0089543549891161651, 0.61726085801840558}",
      "hasCurveFrom": true,
      "hasCurveTo": true,
      "point": "{0.0079606262765823371, 0.62232490419227227}"
    },
    {
      "_class": "curvePoint",
      "cornerRadius": 0,
      "curveFrom": "{0.006470033207781594, 0.63010445338691212}",
      "curveMode": 4,
      "curveTo": "{0.0068675246927973844, 0.62709538247200847}",
      "hasCurveFrom": true,
      "hasCurveTo": true,
      "point": "{0.0065694060790327177, 0.62951731759864293}"
    },
    {
      "_class": "curvePoint",
      "cornerRadius": 0,
      "curveFrom": "{0.0043832029114515168, 0.64221412902008412}",
      "curveMode": 3,
      "curveTo": "{0.0063706603365304704, 0.63076498114872226}",
      "hasCurveFrom": true,
      "hasCurveTo": true,
      "point": "{0.0062712874652680502, 0.63135211693699977}"
    },
    {
      "_class": "curvePoint",
      "cornerRadius": 0,
      "curveFrom": "{0.0017995082588658233, 0.66606652041874015}",
      "curveMode": 2,
      "curveTo": "{0.0029919827139018983, 0.65300274912962752}",
      "hasCurveFrom": true,
      "hasCurveTo": true,
      "point": "{0.0019982540013680698, 0.66371797726563841}"
    },
    {
      "_class": "curvePoint",
      "cornerRadius": 0,
      "curveFrom": "{0.00050766093256732778, 0.68155222683448724}",
      "curveMode": 2,
      "curveTo": "{0.0016007625163635766, 0.66826827962476842}",
      "hasCurveFrom": true,
      "hasCurveTo": true,
      "point": "{0.0014020167738500325, 0.67061682277787027}"
    },
    {
      "_class": "curvePoint",
      "cornerRadius": 0,
      "curveFrom": "{0.00040828806131620442, 0.8223914240468877}",
      "curveMode": 3,
      "curveTo": "{-8.8576294950709663e-05, 0.69256102286463683}",
      "hasCurveFrom": true,
      "hasCurveTo": true,
      "point": "{1.0796576300413669e-05, 0.70334964297418856}"
    },
    {
      "_class": "curvePoint",
      "cornerRadius": 0,
      "curveFrom": "{0.1490701034565102, 0.9455431556375129}",
      "curveMode": 4,
      "curveTo": "{0.057348943289554269, 0.90620505782310978}",
      "hasCurveFrom": false,
      "hasCurveTo": true,
      "point": "{0.1490701034565102, 0.9455431556375129}"
    },
    {
      "_class": "curvePoint",
      "cornerRadius": 0,
      "curveFrom": "{0.18434747275149499, 0.96066190218558856}",
      "curveMode": 4,
      "curveTo": "{0.27596926004719979, 1}",
      "hasCurveFrom": true,
      "hasCurveTo": false,
      "point": "{0.27596926004719979, 1}"
    },
    {
      "_class": "curvePoint",
      "cornerRadius": 0,
      "curveFrom": "{0.12681058029573891, 0.74701786722712393}",
      "curveMode": 3,
      "curveTo": "{0.1273074446520058, 0.87692166038290742}",
      "hasCurveFrom": true,
      "hasCurveTo": true,
      "point": "{0.12690995316699002, 0.75787987931019996}"
    },
    {
      "_class": "curvePoint",
      "cornerRadius": 0,
      "curveFrom": "{0.12849991910704189, 0.72279851596078815}",
      "curveMode": 2,
      "curveTo": "{0.12740681752325694, 0.73608246317050696}",
      "hasCurveFrom": true,
      "hasCurveTo": true,
      "point": "{0.12830117336453964, 0.72507366714034904}"
    },
    {
      "_class": "curvePoint",
      "cornerRadius": 0,
      "curveFrom": "{0.12889741059205767, 0.71824821360165814}",
      "curveMode": 4,
      "curveTo": "{0.12869866484955544, 0.72052336478121892}",
      "hasCurveFrom": false,
      "hasCurveTo": true,
      "point": "{0.12889741059205767, 0.71824821360165814}"
    }
  ],
  "resizingConstraint": 63,
  "resizingType": 0,
  "rotation": 0,
  "shouldBreakMaskChain": false,
  "style": {
    "_class": "style",
    "do_objectID": "A1B4EA89-B11F-48B1-88B4-26710505DFC8",
    "endMarkerType": 0,
    "fills": [
      {
        "_class": "fill",
        "color": {
          "_class": "color",
          "alpha": 1,
          "blue": 0.031,
          "green": 0.235,
          "red": 0.749
        },
        "fillType": 0,
        "isEnabled": true,
        "noiseIndex": 0,
        "noiseIntensity": 0,
        "patternFillType": 1,
        "patternTileScale": 1
      }
    ],
    "miterLimit": 10,
    "startMarkerType": 0,
    "windingRule": 1
  }
}