{
  "_class": "shapePath",
  "booleanOperation": -1,
  "clippingMaskMode": 0,
  "do_objectID": "02B3D6C3-A175-4823-9B21-076D0DC328FA",
  "edited": true,
  "exportOptions": {
    "_class": "exportOptions",
    "do_objectID": "56BEF003-1DFA-4F34-ABCB-345E0AD2F7B7",
    "exportFormats": [
    ],
    "includedLayerIds": [
    ],
    "layerOptions": 0,
    "shouldTrim": false
  },
  "frame": {
    "_class": "rect",
    "constrainProportions": false,
    "do_objectID": "9B0E1621-1C48-4958-9D46-03DAA7B64CBD",
    "height": 1.579409351134757,
    "width": 8.674772798626035,
    "x": 10.45177256381591,
    "y": 99.35237896029655
  },
  "hasClippingMask": false,
  "isClosed": false,
  "isFixedToViewport": false,
  "isFlippedHorizontal": false,
  "isFlippedVertical": false,
  "isLocked": false,
  "isVisible": true,
  "layerListExpandedType": 0,
  "name": "Path 78",
  "nameIsFixed": false,
  "pointRadiusBehaviour": 1,
  "points": [
    {
      "_class": "curvePoint",
      "cornerRadius": 0,
      "curveFrom": "{0.15309168134856846, 0.1530916813485699}",
      "curveMode": 1,
      "curveTo": "{0, 0}",
      "hasCurveFrom": false,
      "hasCurveTo": false,
      "point": "{0, 0}"
    },
    {
      "_class": "curvePoint",
      "cornerRadius": 0,
      "curveFrom": "{0.63495011160724368, 0.86815784493588111}",
      "curveMode": 2,
      "curveTo": "{0.27446680763771736, 0.50767454096635112}",
      "hasCurveFrom": true,
      "hasCurveTo": true,
      "point": "{0.45470845962248052, 0.68791619295111617}"
    },
    {
      "_class": "curvePoint",
      "cornerRadius": 0,
      "curveFrom": "{0.99999999999999489, 1.0000000000000044}",
      "curveMode": 1,
      "curveTo": "{0.81975834801523173, 0.81975834801523961}",
      "hasCurveFrom": false,
      "hasCurveTo": false,
      "point": "{0.99999999999999489, 1.0000000000000044}"
    }
  ],
  "resizingConstraint": 63,
  "resizingType": 0,
  "rotation": 0,
  "shouldBreakMaskChain": false,
  "style": {
    "_class": "style",
    "borderOptions": {
      "_class": "borderOptions",
      "dashPattern": [
      ],
      "do_objectID": "4BB47A60-7D28-4A5C-9CD8-031D39FD59FA",
      "isEnabled": false,
      "lineCapStyle": 1,
      "lineJoinStyle": 1
    },
    "borders": [
      {
        "_class": "border",
        "color": {
          "_class": "color",
          "alpha": 1,
          "blue": 0.7411764705882353,
          "green": 0.6392156862745098,
          "red": 0.6196078431372549
        },
        "fillType": 0,
        "isEnabled": true,
        "position": 0,
        "thickness": 1
      }
    ],
    "do_objectID": "65328FA9-3BAB-4CF9-85C5-1A57315C6163",
    "endMarkerType": 0,
    "miterLimit": 10,
    "startMarkerType": 0,
    "windingRule": 0
  }
}