{
  "_class": "shapeGroup",
  "booleanOperation": -1,
  "clippingMaskMode": 0,
  "do_objectID": "53FF275E-4ABF-4A85-B013-FAD20ADAE452",
  "exportOptions": {
    "_class": "exportOptions",
    "do_objectID": "07BE0B66-9D05-4F17-8EFA-C3FA7CE6461D",
    "exportFormats": [
    ],
    "includedLayerIds": [
    ],
    "layerOptions": 0,
    "shouldTrim": false
  },
  "frame": {
    "_class": "rect",
    "constrainProportions": false,
    "do_objectID": "381494F7-8638-4733-9002-771C6D0EA003",
    "height": 147.2510031686438,
    "width": 235.7245397009758,
    "x": 126.1631768953069,
    "y": 97.06093898227562
  },
  "hasClickThrough": false,
  "hasClippingMask": false,
  "isFixedToViewport": false,
  "isFlippedHorizontal": false,
  "isFlippedVertical": false,
  "isLocked": false,
  "isVisible": true,
  "layerListExpandedType": 1,
  "layers": [
    {
      "class": "shapePath",
      "id": "7C4ADF68-1BFE-4CDC-9EE6-123C81785440"
    }
  ],
  "name": "Shape",
  "nameIsFixed": false,
  "resizingConstraint": 63,
  "resizingType": 0,
  "rotation": 0,
  "shouldBreakMaskChain": false,
  "style": {
    "_class": "style",
    "do_objectID": "99B439B9-31EE-4A9A-87D8-BA9FD468D493",
    "endMarkerType": 0,
    "fills": [
      {
        "_class": "fill",
        "color": {
          "_class": "color",
          "alpha": 1,
          "blue": 0.3411764705882353,
          "green": 0.3411764705882353,
          "red": 0.3490196078431372
        },
        "fillType": 0,
        "isEnabled": true,
        "noiseIndex": 0,
        "noiseIntensity": 0,
        "patternFillType": 1,
        "patternTileScale": 1
      }
    ],
    "miterLimit": 10,
    "startMarkerType": 0,
    "windingRule": 0
  },
  "windingRule": 0
}