{
  "_class": "shapeGroup",
  "booleanOperation": -1,
  "clippingMaskMode": 0,
  "do_objectID": "F7125884-1FA4-4302-82D0-333226321609",
  "exportOptions": {
    "_class": "exportOptions",
    "do_objectID": "BD7B3A6A-D54E-482C-9B61-2F782CA1D7F1",
    "exportFormats": [
    ],
    "includedLayerIds": [
    ],
    "layerOptions": 0,
    "shouldTrim": false
  },
  "frame": {
    "_class": "rect",
    "constrainProportions": false,
    "do_objectID": "8FA86C5D-969B-4766-8469-52FF04877226",
    "height": 1,
    "width": 139.4906137184114,
    "x": 0.3990974729241686,
    "y": 169.0942771084339
  },
  "hasClickThrough": false,
  "hasClippingMask": false,
  "isFixedToViewport": false,
  "isFlippedHorizontal": false,
  "isFlippedVertical": false,
  "isLocked": false,
  "isVisible": true,
  "layerListExpandedType": 0,
  "layers": [
    {
      "class": "rectangle",
      "id": "C140A0FB-C007-462C-89AB-1CC439936321"
    }
  ],
  "name": "Rectangle-path",
  "nameIsFixed": false,
  "resizingConstraint": 63,
  "resizingType": 0,
  "rotation": 0,
  "shouldBreakMaskChain": false,
  "style": {
    "_class": "style",
    "do_objectID": "F0646434-678A-4BE6-85FF-2791F5725A5E",
    "endMarkerType": 0,
    "fills": [
      {
        "_class": "fill",
        "color": {
          "_class": "color",
          "alpha": 1,
          "blue": 0.3411764705882353,
          "green": 0.3411764705882353,
          "red": 0.3490196078431372
        },
        "fillType": 0,
        "isEnabled": true,
        "noiseIndex": 0,
        "noiseIntensity": 0,
        "patternFillType": 1,
        "patternTileScale": 1
      }
    ],
    "miterLimit": 10,
    "startMarkerType": 0,
    "windingRule": 0
  },
  "windingRule": 0
}