{
  "_class": "group",
  "booleanOperation": -1,
  "clippingMaskMode": 0,
  "do_objectID": "0B15ECD5-BA1A-4FB2-A59F-37DAE999BD93",
  "exportOptions": {
    "_class": "exportOptions",
    "do_objectID": "6EEB5ECF-87AD-40AF-AAE9-7D4FFF06D942",
    "exportFormats": [
    ],
    "includedLayerIds": [
    ],
    "layerOptions": 0,
    "shouldTrim": false
  },
  "frame": {
    "_class": "rect",
    "constrainProportions": false,
    "do_objectID": "2B79AA7E-11E5-4359-89FD-9C8C4BDE6DF8",
    "height": 31,
    "width": 270,
    "x": 0,
    "y": 0
  },
  "hasClickThrough": false,
  "hasClippingMask": false,
  "isFixedToViewport": false,
  "isFlippedHorizontal": false,
  "isFlippedVertical": false,
  "isLocked": false,
  "isVisible": true,
  "layerListExpandedType": 0,
  "layers": [
    {
      "class": "rectangle",
      "id": "BBD3F9DA-6549-4FB7-8C83-00620E2147B8"
    },
    {
      "class": "text",
      "id": "122D0937-184B-47F6-BB81-492DBC073DE4"
    }
  ],
  "name": "↳ Action 2",
  "nameIsFixed": false,
  "resizingConstraint": 63,
  "resizingType": 0,
  "rotation": 0,
  "shouldBreakMaskChain": false,
  "style": {
    "_class": "style",
    "do_objectID": "BD0F0C92-9D5A-4E90-ACD3-B4F19F4D4E59",
    "endMarkerType": 0,
    "miterLimit": 10,
    "startMarkerType": 0,
    "windingRule": 1
  }
}