{
  "_class": "text",
  "attributedString": {
    "_class": "attributedString",
    "attributes": [
      {
        "_class": "stringAttribute",
        "attributes": {
          "MSAttributedStringColorAttribute": {
            "_class": "color",
            "alpha": 1,
            "blue": 0.4039215686,
            "green": 0.1725490196,
            "red": 0.1294117647
          },
          "MSAttributedStringFontAttribute": {
            "_class": "fontDescriptor",
            "attributes": {
              "name": "PingFangSC-Regular",
              "size": 16
            }
          },
          "kerning": 0,
          "paragraphStyle": {
            "_class": "paragraphStyle",
            "alignment": 0,
            "allowsDefaultTighteningForTruncation": 0,
            "maximumLineHeight": 16,
            "minimumLineHeight": 16
          }
        },
        "length": 28,
        "location": 0
      }
    ],
    "string": "https://mainnet-eos.token.im"
  },
  "automaticallyDrawOnUnderlyingPath": false,
  "booleanOperation": 0,
  "do_objectID": "F84E3A04-6DC6-4399-B8FE-F590F0E008A5",
  "dontSynchroniseWithSymbol": false,
  "exportOptions": {
    "_class": "exportOptions",
    "do_objectID": "087DA10E-87D2-4039-97C0-588C1E3C94DA",
    "exportFormats": [
    ],
    "includedLayerIds": [
    ],
    "layerOptions": 0,
    "shouldTrim": false
  },
  "frame": {
    "_class": "rect",
    "constrainProportions": false,
    "do_objectID": "0A3B1F81-80D2-40D9-A8E6-8014C5C33695",
    "height": 16,
    "width": 221,
    "x": 1,
    "y": 4
  },
  "glyphBounds": "{{0, 0}, {220, 18}}",
  "isFixedToViewport": false,
  "isFlippedHorizontal": false,
  "isFlippedVertical": false,
  "isLocked": false,
  "isVisible": true,
  "layerListExpandedType": 0,
  "lineSpacingBehaviour": 2,
  "name": "https://mainnet-eos.",
  "nameIsFixed": false,
  "resizingConstraint": 47,
  "resizingType": 0,
  "rotation": 0,
  "shouldBreakMaskChain": false,
  "style": {
    "_class": "style",
    "do_objectID": "8638F421-50B2-466F-9534-286596853590",
    "endMarkerType": 0,
    "miterLimit": 10,
    "sharedObjectID": "B2740C17-6A86-456B-9ED3-B9225C9BFF02",
    "startMarkerType": 0,
    "textStyle": {
      "_class": "textStyle",
      "do_objectID": "BED56A09-2F13-497A-AC85-55C3894126F2",
      "encodedAttributes": {
        "MSAttributedStringColorAttribute": {
          "_class": "color",
          "alpha": 1,
          "blue": 0.4039215686,
          "green": 0.1725490196,
          "red": 0.1294117647
        },
        "MSAttributedStringFontAttribute": {
          "_class": "fontDescriptor",
          "attributes": {
            "name": "PingFangSC-Regular",
            "size": 16
          }
        },
        "kerning": 0,
        "paragraphStyle": {
          "_class": "paragraphStyle",
          "alignment": 0,
          "allowsDefaultTighteningForTruncation": 0,
          "maximumLineHeight": 16,
          "minimumLineHeight": 16
        }
      },
      "verticalAlignment": 0
    },
    "windingRule": 1
  },
  "textBehaviour": 0,
  "userInfo": {
    "com.animaapp.stc-sketch-plugin": {
      "kModelPropertiesKey": {
        "isAutoWidth": 1
      }
    }
  }
}