{
  "_class": "group",
  "booleanOperation": 0,
  "do_objectID": "CA10B8E9-F41F-4882-998D-0651BAC02AD4",
  "exportOptions": {
    "_class": "exportOptions",
    "do_objectID": "9055C0D7-5748-4CFF-846D-7EBD50E9FC93",
    "exportFormats": [
    ],
    "includedLayerIds": [
    ],
    "layerOptions": 0,
    "shouldTrim": false
  },
  "flow": {
    "_class": "MSImmutableFlowConnection",
    "animationType": 0,
    "destinationArtboardID": "0ECDDB61-788E-48B6-83E5-4C26EA3B6FC9",
    "do_objectID": "60A3ED0E-0826-4440-A8CE-B34897C523FC"
  },
  "frame": {
    "_class": "rect",
    "constrainProportions": false,
    "do_objectID": "9B52D35B-D23C-4406-BABB-0E13ADC96A30",
    "height": 44,
    "width": 311,
    "x": 16,
    "y": 116
  },
  "hasClickThrough": false,
  "isFixedToViewport": false,
  "isFlippedHorizontal": false,
  "isFlippedVertical": false,
  "isLocked": false,
  "isVisible": true,
  "layerListExpandedType": 0,
  "layers": [
    {
      "class": "shapeGroup",
      "id": "D34691E1-67BD-479C-8F86-5279A6311A3F"
    },
    {
      "class": "text",
      "id": "2E1989A3-BDD9-40CB-8F8C-88652655AC97"
    }
  ],
  "name": "button",
  "nameIsFixed": false,
  "resizingConstraint": 63,
  "resizingType": 0,
  "rotation": 0,
  "shouldBreakMaskChain": false,
  "style": {
    "_class": "style",
    "do_objectID": "A4367066-51F1-4CB9-836A-AA97B750B511",
    "endMarkerType": 0,
    "miterLimit": 10,
    "startMarkerType": 0,
    "windingRule": 1
  }
}