{
  "_class": "group",
  "booleanOperation": -1,
  "do_objectID": "3A22D75A-4299-4C12-95E2-616333ABD1EF",
  "exportOptions": {
    "_class": "exportOptions",
    "do_objectID": "F9985CB9-80A2-4359-B91A-3614C0CE7B86",
    "exportFormats": [
    ],
    "includedLayerIds": [
    ],
    "layerOptions": 0,
    "shouldTrim": false
  },
  "frame": {
    "_class": "rect",
    "constrainProportions": true,
    "do_objectID": "E2E53B78-526A-483F-A6BB-019C205494FF",
    "height": 200,
    "width": 335,
    "x": 0,
    "y": 0
  },
  "hasClickThrough": false,
  "isFixedToViewport": false,
  "isFlippedHorizontal": false,
  "isFlippedVertical": false,
  "isLocked": false,
  "isVisible": true,
  "layerListExpandedType": 2,
  "layers": [
    {
      "class": "group",
      "id": "47FA027A-4741-41D7-9422-7E7F1E225D08"
    },
    {
      "class": "group",
      "id": "19E6338C-27CC-4C93-B096-D57AB052DC08"
    },
    {
      "class": "group",
      "id": "72170F71-E91B-4E08-9855-4E7840CB3542"
    },
    {
      "class": "bitmap",
      "id": "94CA0047-AE36-432D-A9D6-ACE432403E8B"
    },
    {
      "class": "group",
      "id": "671D315D-6B1F-4E0E-87CC-7AD647CB07F1"
    },
    {
      "class": "group",
      "id": "263C48FF-BAB7-435D-91AC-79E422DAF60A"
    },
    {
      "class": "group",
      "id": "BBA58727-04F4-463A-9392-30762F8778D2"
    }
  ],
  "name": "card",
  "nameIsFixed": true,
  "resizingConstraint": 63,
  "resizingType": 0,
  "rotation": 0,
  "shouldBreakMaskChain": false,
  "style": {
    "_class": "style",
    "do_objectID": "2CF9DE55-A275-4187-8960-5AA7AC09F0E9",
    "endMarkerType": 0,
    "miterLimit": 10,
    "startMarkerType": 0,
    "windingRule": 1
  }
}