{
  "_class": "group",
  "booleanOperation": 0,
  "do_objectID": "FC3E5C22-63C4-4631-A7B2-FDD0937C4E9A",
  "exportOptions": {
    "_class": "exportOptions",
    "do_objectID": "D70B03E4-64D5-49F5-82A3-782E1FAF0058",
    "exportFormats": [
    ],
    "includedLayerIds": [
    ],
    "layerOptions": 0,
    "shouldTrim": false
  },
  "flow": {
    "_class": "MSImmutableFlowConnection",
    "animationType": 0,
    "destinationArtboardID": "5E8486F7-DDEC-4620-825A-F475FF92538E",
    "do_objectID": "89C68076-713D-4745-8F65-3C2D9ACB3AC9"
  },
  "frame": {
    "_class": "rect",
    "constrainProportions": false,
    "do_objectID": "104FDCC7-A8C8-4560-9382-CE951FE94E42",
    "height": 108,
    "width": 375,
    "x": 0,
    "y": 520
  },
  "hasClickThrough": false,
  "isFixedToViewport": false,
  "isFlippedHorizontal": false,
  "isFlippedVertical": false,
  "isLocked": false,
  "isVisible": true,
  "layerListExpandedType": 0,
  "layers": [
    {
      "class": "text",
      "id": "585F2F55-7134-4EEB-8F0E-2A329BF4E627"
    },
    {
      "class": "text",
      "id": "DACCE5FE-548C-47A9-8030-A10AFD3C745A"
    },
    {
      "class": "shapeGroup",
      "id": "520A847B-E607-48D5-8F39-457AD1772C83"
    },
    {
      "class": "shapeGroup",
      "id": "03F86D45-E6A3-4983-83C3-C36DB18D2953"
    }
  ],
  "name": "list1",
  "nameIsFixed": true,
  "resizingConstraint": 63,
  "resizingType": 0,
  "rotation": 0,
  "shouldBreakMaskChain": false,
  "style": {
    "_class": "style",
    "do_objectID": "B227807A-ED2E-48D6-ACA3-E3A691838221",
    "endMarkerType": 0,
    "miterLimit": 10,
    "startMarkerType": 0,
    "windingRule": 1
  },
  "userInfo": {
    "com.animaapp.stc-sketch-plugin": {
      "kModelPropertiesKey": {
      }
    }
  }
}