{
  "_class": "group",
  "booleanOperation": 0,
  "do_objectID": "293F9A89-F01D-493A-989A-EB2C8CBF6388",
  "exportOptions": {
    "_class": "exportOptions",
    "do_objectID": "03D78B9B-103F-442F-83FC-CC5568DBF387",
    "exportFormats": [
    ],
    "includedLayerIds": [
    ],
    "layerOptions": 0,
    "shouldTrim": false
  },
  "frame": {
    "_class": "rect",
    "constrainProportions": false,
    "do_objectID": "DC4B9378-932E-49CE-839D-CC48D9D73097",
    "height": 48,
    "width": 343,
    "x": 0,
    "y": 92
  },
  "hasClickThrough": false,
  "isFixedToViewport": false,
  "isFlippedHorizontal": false,
  "isFlippedVertical": false,
  "isLocked": false,
  "isVisible": true,
  "layerListExpandedType": 0,
  "layers": [
    {
      "class": "shapeGroup",
      "id": "585A2328-01D9-4258-BB90-FB80EE81691F"
    },
    {
      "class": "text",
      "id": "CDAE2582-5519-46C8-A731-1A40DB7FA683"
    },
    {
      "class": "symbolInstance",
      "id": "54800CED-7BE5-4B9E-A081-247D407A6715"
    }
  ],
  "name": "Group 3",
  "nameIsFixed": false,
  "resizingConstraint": 63,
  "resizingType": 0,
  "rotation": 0,
  "shouldBreakMaskChain": false,
  "style": {
    "_class": "style",
    "do_objectID": "4DE78C12-CE18-43B5-92F9-8CFCF368BA4E",
    "endMarkerType": 0,
    "miterLimit": 10,
    "startMarkerType": 0,
    "windingRule": 1
  },
  "userInfo": {
    "com.animaapp.stc-sketch-plugin": {
      "kModelPropertiesKey": {
      }
    }
  }
}