{
  "_class": "shapeGroup",
  "booleanOperation": 0,
  "clippingMaskMode": 0,
  "do_objectID": "5B56AEFA-57A5-4EA1-974D-767ED68DEF83",
  "exportOptions": {
    "_class": "exportOptions",
    "do_objectID": "7AB29216-4BD4-421F-905E-4BEDCFFC29FD",
    "exportFormats": [
    ],
    "includedLayerIds": [
    ],
    "layerOptions": 0,
    "shouldTrim": false
  },
  "frame": {
    "_class": "rect",
    "constrainProportions": true,
    "do_objectID": "53713273-F8E3-4FF0-A490-DC141E349A74",
    "height": 10,
    "width": 20,
    "x": 1,
    "y": 7
  },
  "hasClickThrough": false,
  "hasClippingMask": false,
  "isFixedToViewport": false,
  "isFlippedHorizontal": true,
  "isFlippedVertical": false,
  "isLocked": false,
  "isVisible": true,
  "layerListExpandedType": 0,
  "layers": [
    {
      "class": "shapePath",
      "id": "6BA293F6-79BA-487D-B5DF-A3C9A51987DE"
    }
  ],
  "name": "ic_notify_back",
  "nameIsFixed": true,
  "resizingConstraint": 63,
  "resizingType": 0,
  "rotation": 90,
  "shouldBreakMaskChain": false,
  "style": {
    "_class": "style",
    "do_objectID": "B84DD3AF-3011-4F36-9C48-027297DF31B0",
    "endMarkerType": 0,
    "fills": [
      {
        "_class": "fill",
        "color": {
          "_class": "color",
          "alpha": 1,
          "blue": 0.3764705882352941,
          "green": 0.3764705882352941,
          "red": 0.3764705882352941
        },
        "fillType": 0,
        "isEnabled": true,
        "noiseIndex": 0,
        "noiseIntensity": 0,
        "patternFillType": 1,
        "patternTileScale": 1
      }
    ],
    "miterLimit": 10,
    "startMarkerType": 0,
    "windingRule": 0
  },
  "windingRule": 0
}