{
  "_class": "group",
  "booleanOperation": 0,
  "do_objectID": "99134D6E-9319-40E0-90E7-57F1A6C1713B",
  "exportOptions": {
    "_class": "exportOptions",
    "exportFormats": [
    ],
    "includedLayerIds": [
    ],
    "layerOptions": 0,
    "shouldTrim": false
  },
  "frame": {
    "_class": "rect",
    "constrainProportions": false,
    "height": 106,
    "width": 343,
    "x": 16,
    "y": 84
  },
  "hasClickThrough": false,
  "isFixedToViewport": false,
  "isFlippedHorizontal": false,
  "isFlippedVertical": false,
  "isLocked": false,
  "isVisible": true,
  "layerListExpandedType": 1,
  "layers": [
    {
      "class": "shapeGroup",
      "id": "5D77A40F-5067-4473-BD67-002DAAF7DA75"
    },
    {
      "class": "text",
      "id": "9AFC34A1-9FB6-4FDE-8BC9-96116127E7CF"
    },
    {
      "class": "text",
      "id": "9B2CCC77-A419-4D2D-9606-04F0292C13FB"
    },
    {
      "class": "text",
      "id": "7E3768CA-510F-463A-8334-E0486ED9CD32"
    }
  ],
  "name": "Group 3",
  "nameIsFixed": false,
  "resizingConstraint": 63,
  "resizingType": 0,
  "rotation": 0,
  "shouldBreakMaskChain": false,
  "style": {
    "_class": "style",
    "endMarkerType": 0,
    "miterLimit": 10,
    "startMarkerType": 0,
    "windingRule": 1
  },
  "userInfo": {
    "com.animaapp.stc-sketch-plugin": {
      "kModelPropertiesKey": {
      }
    }
  }
}