{
  "_class": "shapeGroup",
  "booleanOperation": -1,
  "clippingMaskMode": 0,
  "do_objectID": "2D597301-D6B8-4B50-8779-CC310EF5EB5C",
  "exportOptions": {
    "_class": "exportOptions",
    "do_objectID": "424A3FC7-6799-48D6-BDEB-E9880CC2A5E5",
    "exportFormats": [
    ],
    "includedLayerIds": [
    ],
    "layerOptions": 0,
    "shouldTrim": false
  },
  "frame": {
    "_class": "rect",
    "constrainProportions": false,
    "do_objectID": "7C9F7937-33B5-4BB8-932B-6AE4DF573060",
    "height": 31.9783125,
    "width": 31.97834375,
    "x": 0.01078125000003638,
    "y": 0.01084375000027649
  },
  "hasClickThrough": false,
  "hasClippingMask": false,
  "isFixedToViewport": false,
  "isFlippedHorizontal": false,
  "isFlippedVertical": false,
  "isLocked": false,
  "isVisible": true,
  "layerListExpandedType": 0,
  "layers": [
    {
      "class": "shapePath",
      "id": "EAF81EA1-97E3-4A4C-AC5E-DA57B9520EB4"
    },
    {
      "class": "shapePath",
      "id": "102479C5-B0CE-413E-B721-7530E030F09C"
    }
  ],
  "name": "Shape",
  "nameIsFixed": false,
  "resizingConstraint": 63,
  "resizingType": 0,
  "rotation": 0,
  "shouldBreakMaskChain": false,
  "style": {
    "_class": "style",
    "do_objectID": "760A8ACE-8623-404A-B776-9A89B2561149",
    "endMarkerType": 0,
    "fills": [
      {
        "_class": "fill",
        "color": {
          "_class": "color",
          "alpha": 1,
          "blue": 0,
          "green": 0,
          "red": 0
        },
        "fillType": 0,
        "isEnabled": true,
        "noiseIndex": 0,
        "noiseIntensity": 0,
        "patternFillType": 1,
        "patternTileScale": 1
      }
    ],
    "miterLimit": 10,
    "startMarkerType": 0,
    "windingRule": 0
  },
  "windingRule": 0
}