{
  "_class": "symbolInstance",
  "booleanOperation": 0,
  "do_objectID": "5593A055-3CA1-48B0-A064-64577A75A33C",
  "exportOptions": {
    "_class": "exportOptions",
    "do_objectID": "CD01E9F1-5A0D-4D4F-BC1F-EF940AA385A3",
    "exportFormats": [
    ],
    "includedLayerIds": [
    ],
    "layerOptions": 0,
    "shouldTrim": false
  },
  "frame": {
    "_class": "rect",
    "constrainProportions": false,
    "do_objectID": "318BCECD-0313-496B-A073-B4B155FFB77F",
    "height": 24,
    "width": 24,
    "x": 7,
    "y": 32
  },
  "horizontalSpacing": 0,
  "isFixedToViewport": false,
  "isFlippedHorizontal": false,
  "isFlippedVertical": false,
  "isLocked": false,
  "isVisible": true,
  "layerListExpandedType": 0,
  "name": "ic_notify_back_white",
  "nameIsFixed": false,
  "overrideValues": [
  ],
  "resizingConstraint": 63,
  "resizingType": 0,
  "rotation": 0,
  "scale": 1,
  "shouldBreakMaskChain": false,
  "style": {
    "_class": "style",
    "do_objectID": "749C7AE1-A3AB-4265-B408-4DDFED2391A6",
    "endMarkerType": 0,
    "miterLimit": 10,
    "startMarkerType": 0,
    "windingRule": 1
  },
  "symbolID": "1BEB9E32-14E6-4E5C-919B-340DBF36082A",
  "verticalSpacing": 0
}