{
  "_class": "group",
  "booleanOperation": 0,
  "do_objectID": "97C94567-E823-4943-B851-0D514F0A6A56",
  "exportOptions": {
    "_class": "exportOptions",
    "do_objectID": "69A597A0-5527-45B9-A57D-771708A32321",
    "exportFormats": [
    ],
    "includedLayerIds": [
    ],
    "layerOptions": 0,
    "shouldTrim": false
  },
  "frame": {
    "_class": "rect",
    "constrainProportions": false,
    "do_objectID": "03B568CF-216A-4F0C-A8FF-1CEADE06CF25",
    "height": 24,
    "width": 171,
    "x": 32,
    "y": 421
  },
  "hasClickThrough": false,
  "isFixedToViewport": false,
  "isFlippedHorizontal": false,
  "isFlippedVertical": false,
  "isLocked": false,
  "isVisible": true,
  "layerListExpandedType": 1,
  "layers": [
    {
      "class": "text",
      "id": "5F457046-AEA1-4512-9819-15F3FBE5B236"
    },
    {
      "class": "symbolInstance",
      "id": "07E616D0-B97C-46EB-BCBF-5567D3CDBA2A"
    }
  ],
  "name": "协议",
  "nameIsFixed": true,
  "resizingConstraint": 63,
  "resizingType": 0,
  "rotation": 0,
  "shouldBreakMaskChain": false,
  "style": {
    "_class": "style",
    "do_objectID": "197FE75F-2CB5-43AD-B8AF-B047228CE45F",
    "endMarkerType": 0,
    "miterLimit": 10,
    "startMarkerType": 0,
    "windingRule": 1
  }
}